Workbook

Sheet Folha
C1: 45658 | D1: 45689 | E1: 45717 | F1: 45748 | G1: 45778 | H1: 45809 | I1: 45839 | J1: 45870 | K1: 45901 | L1: 45931 | M1: 45962 | N1: 45992
A2: Monike Bobroski Nunes
B3: Salário
B4: Alimentação
B5: Transporte
B6: Variável
B7: Férias
B8: 13º Salário
B9: Adiantamentos
C10: =SUM(C2:C9) -> 0 | D10: =SUM(D2:D9) -> 0 | E10: =SUM(E2:E9) -> 0 | F10: =SUM(F2:F9) -> 0 | G10: =SUM(G2:G9) -> 0 | H10: =SUM(H2:H9) -> 0 | I10: =SUM(I2:I9) -> 0 | J10: =SUM(J2:J9) -> 0 | ... N10: =SUM(N2:N9) -> 0
A11: Gabrielle Andrade
B12: Salário | C12: 1647.26 | E12: 1647.26
B13: Comissão | E13: 150
B14: Alimentação | C14: 374 | E14: 484
B15: Transporte | C15: 400 | E15: =551.2+10.8 -> 562
B16: Férias
B17: 13º Salário
B18: Multa/Descontos
B19: Adiantamentos
C20: =SUM(C11:C19) -> 2421.26 | D20: =SUM(D11:D19) -> 0 | E20: =SUM(E11:E19) -> 2843.26 | F20: =SUM(F11:F19) -> 0 | G20: =SUM(G11:G19) -> 0 | H20: =SUM(H11:H19) -> 0 | I20: =SUM(I11:I19) -> 0 | J20: =SUM(J11:J19) -> 0 | ... N20: =SUM(N11:N19) -> 0
A21: Pamela de Araujo Barroso
B22: Salário
B23: Alimentação
B24: Transporte
B25: Férias
B26: 13º Salário
B27: Multa/Descontos
B28: Adiantamentos
C29: =SUM(C21:C28) -> 0 | D29: =SUM(D21:D28) -> 0 | E29: =SUM(E21:E28) -> 0 | F29: =SUM(F21:F28) -> 0 | G29: =SUM(G21:G28) -> 0 | H29: =SUM(H21:H28) -> 0 | I29: =SUM(I21:I28) -> 0 | J29: =SUM(J21:J28) -> 0 | ... N29: =SUM(N21:N28) -> 0
A30: Tamires Caroline Borges Bento Leal
B31: Salário | C31: 604.89 | D31: 951.17 | E31: 3391.46
B32: Comissão | C32: 150
B33: Alimentação | C33: 374
B34: Transporte | C34: =207.2+592 -> 799.2
B35: Férias
B36: 13º Salário
B37: Multa/Descontos
B38: Adiantamentos
C39: =SUM(C30:C38) -> 1928.09 | D39: =SUM(D30:D38) -> 951.17 | E39: =SUM(E30:E38) -> 3391.46 | F39: =SUM(F30:F38) -> 0 | G39: =SUM(G30:G38) -> 0 | H39: =SUM(H30:H38) -> 0 | I39: =SUM(I30:I38) -> 0 | J39: =SUM(J30:J38) -> 0 | ... N39: =SUM(N30:N38) -> 0
A40: Edurado Mancan
B41: Salário | C41: =1500+147.26 -> 1647.26 | E41: 1647.26
B42: Comissão | C42: =800+182 -> 982 | E42: =600+1820.5+150 -> 2570.5
B43: Alimentação | C43: 374 | E43: 484
B44: Transporte | C44: 580 | E44: =207.2+785.2+10.8 -> 1003.2
B45: Férias
B46: 13º Salário
B47: Multa/Descontos
B48: Adiantamentos
C49: =SUM(C40:C48) -> 3583.26 | D49: =SUM(D40:D48) -> 0 | E49: =SUM(E40:E48) -> 5704.96 | F49: =SUM(F40:F48) -> 0 | G49: =SUM(G40:G48) -> 0 | H49: =SUM(H40:H48) -> 0 | I49: =SUM(I40:I48) -> 0 | J49: =SUM(J40:J48) -> 0 | ... N49: =SUM(N40:N48) -> 0
A50: Vitor Hoffmann
B51: Salário | C51: 1647.26 | D51: 300 | E51: =1647.26-300 -> 1347.26
B52: Comissão | C52: 860 | E52: 2612.5
B53: Alimentação | C53: 374 | E53: 484
B54: Transporte | C54: 200 | E54: =275.6+5.4 -> 281
B55: Férias
B56: 13º Salário
B57: Multa/Descontos
B58: Adiantamentos
C59: =SUM(C50:C58) -> 3081.26 | D59: =SUM(D50:D58) -> 300 | E59: =SUM(E50:E58) -> 4724.76 | F59: =SUM(F50:F58) -> 0 | G59: =SUM(G50:G58) -> 0 | H59: =SUM(H50:H58) -> 0 | I59: =SUM(I50:I58) -> 0 | J59: =SUM(J50:J58) -> 0 | ... N59: =SUM(N50:N58) -> 0
A60: Josselaine Rodrigues de Souza
B61: Salário
B62: Comissão
B63: Alimentação
B64: Transporte
B65: Férias
B66: 13º Salário
B67: Multa/Descontos
B68: Adiantamentos
C69: =SUM(C61:C68) -> 0 | D69: =SUM(D61:D68) -> 0 | E69: =SUM(E61:E68) -> 0 | F69: =SUM(F61:F68) -> 0 | G69: =SUM(G61:G68) -> 0 | H69: =SUM(H61:H68) -> 0 | I69: =SUM(I61:I68) -> 0 | J69: =SUM(J61:J68) -> 0 | ... N69: =SUM(N61:N68) -> 0
A71: Jordana de Jesus Souza da Silva
B72: Salário
B73: Comissão
B74: Alimentação
B75: Transporte
B76: Férias
B77: 13º Salário
B78: Multa/Descontos
B79: Adiantamentos
C80: =SUM(C72:C79) -> 0 | D80: =SUM(D72:D79) -> 0 | E80: =SUM(E72:E79) -> 0 | F80: =SUM(F72:F79) -> 0 | G80: =SUM(G72:G79) -> 0 | H80: =SUM(H72:H79) -> 0 | I80: =SUM(I72:I79) -> 0 | J80: =SUM(J72:J79) -> 0 | ... N80: =SUM(N72:N79) -> 0
A81: Pamela Paixão Santos
B82: Salário | C82: 1647.26 | D82: 3675.89 | E82: 460
B83: Comissão | C83: =400+486 -> 886
B84: Alimentação | C84: 198
B85: Transporte | C85: 200
B86: Férias
B87: 13º Salário
B88: Multa/Descontos
B89: Adiantamentos
C90: =SUM(C82:C89) -> 2931.26 | D90: =SUM(D82:D89) -> 3675.89 | E90: =SUM(E82:E89) -> 460 | F90: =SUM(F82:F89) -> 0 | G90: =SUM(G82:G89) -> 0 | H90: =SUM(H82:H89) -> 0 | I90: =SUM(I82:I89) -> 0 | J90: =SUM(J82:J89) -> 0 | ... N90: =SUM(N82:N89) -> 0
A91: Gustavo
B92: Salário
B93: Comissão
B94: Alimentação | E94: 484
B95: Transporte | E95: 657.2
B96: Férias
B97: 13º Salário
B98: Multa/Descontos
B99: Adiantamentos
C100: =SUM(C92:C99) -> 0 | D100: =SUM(D92:D99) -> 0 | E100: =SUM(E92:E99) -> 1141.2 | F100: =SUM(F92:F99) -> 0 | G100: =SUM(G92:G99) -> 0 | H100: =SUM(H92:H99) -> 0 | I100: =SUM(I92:I99) -> 0 | J100: =SUM(J92:J99) -> 0 | ... N100: =SUM(N92:N99) -> 0
A101: Consultor 2
...

Sheet FATURAMENTO 
B1: 46023 | E1: 46054 | H1: 46082 | K1: 46113 | N1: 46143 | Q1: 46174 | T1: 46204 | W1: 46235 | Z1: 46266 | AC1: 46296 | AF1: 46327 | AI1: 46357
A2: RECEITAS
A4: CAIXA
A6: Goethe Imóveis Pipeimobi | B6: 4006.34
A7: Goethe Imóveis Pipeimobi | B7: 3346.4
A8: Ato do contrato 189591 - Praia e Belas 1762 106 - Cleiton - Repassado no mesmo dia | B8: 20000
A9: Goethe Imóveis Pipeimobi | E9: 3000
A10: Goethe Imóveis Pipeimobi | E10: 2539.21
A11: Goethe Imóveis Pipeimobi | E11: 5000
A12: Goethe Imóveis Pipeimobi | H12: 2741.06
A13: Crédito não identificado ??????? | H13: 492.9
A14: Crédito não identificado ??????? | H14: 990
A15: Crédito não identificado ??????? | H15: 4200
A16: Crédito não identificado ??????? | H16: 1050
A17: Crédito não identificado ??????? | H17: 1470
A24: PIPEIMOB
A26: Antecipação de Comissão - Contrato 448520 - Ferreira Viana, 885, 512 | B26: 1550
A27: Antecipação de Comissão - Contrato 299409 (CT 12564) - Doutor Otávio Santos, 257, 507 | B27: 1130
A28: Antecipação de Comissão - Contrato 719417 - Reverendo Olavo Nunes, 280, 502 | B28: 2100
A29: Antecipação de Comissão - Contrato 308794 - HIPOLITO DA COSTA, 211, 301 | B29: 1510
A30: Crédito do Pipeimob ??????? | B30: 4720
A31: Contrato 147120 - INDEPENDENCIA, 519, 203 - Rosemeri | B31: 9450
A32: Contrato 876859 (CT 12176) - Gabriel Franco da Luz 175, 308 | B32: 2760
A33: Contrato 272703 - GETULIO VARGAS, 1151, 516 | B33: 693.6
A34: Contrato 474600 - Engenheiro Ludolfo Boehl, 931, 13 | B34: 910
A35: Contrato 368073 - DOUTOR POSSIDONIO CUNHA, 719, 2 Parte 1 de 2 | B35: 2414
A36: Contrato 368073 - DOUTOR POSSIDONIO CUNHA, 719, 2 Parte 2 de 2 | B36: 4828
A37: Contrato 448520 - Ferreira Viana, 885, 512 | B37: 1212.46
... A45: Antecipação de Comissão - Contrato 474600 - Engenheiro Ludolfo Boehl, 931, 13 | B45: 3180
A46: Contrato 401279 - JOAO PESSOA, 105, 501, Farroupilha, Porto Alegre - RS, CEP 90040-001 | E46: 413.1
A47: Contrato 415673 - ALMIRANTE ABREU, 354, 801, Rio Branco, Porto Alegre / RS, CEP 90420010 | E47: 13125
A48: Contrato 448520 - Ferreira Viana, 885, 512, Petrópolis, Porto Alegre / RS, CEP 90670-100 | E48: 1896.42
A49: Contrato 474600 - Engenheiro Ludolfo Boehl, 931, 13, Teresópolis, Porto Alegre / RS, CEP 91720150 | E49: 910
A50: Contrato 495832 - Dona Otília, 3804, 401, Santa Tereza, Porto Alegre / RS, CEP 90830580 | E50: 4200
A51: Contrato 748245 - Soledade, 371, 602, Petrópolis, Porto Alegre / RS, CEP 90470-340 | E51: 8925
A52: Contrato 759002 - da Azenha, 1338, 31, Azenha, Porto Alegre / RS, CEP 90160-003 | E52: 4200
A53: Contrato 759847 - Independência, 972, 607, Independência, Porto Alegre / RS, CEP 90035072 | E53: 20592
A54: Devolução de Antecipação de Comissão - 448520 - Ferreira Viana, 885, 512, Petrópolis, Porto Alegre / RS, CEP 90670-100 | E54: -1683.19
A55: Devolução de Antecipação de Comissão - 722551 - GENERAL JOAO TELLES, 68, 502, Bom Fim, Porto Alegre / RS, CEP 90035-120 | E55: -3446.79
A56: Devolução de Antecipação de Comissão - 750147 - Jari, 735, 909, Passo da Areia, Porto Alegre / RS, CEP 91350170 | E56: -6379.45
A57: Devolução de Antecipação de Comissão - 759847 - Independência, 972, 607, Independência, Porto Alegre / RS, CEP 90035072 | E57: -7341.69
A58: Contrato 454042 - CARLOS ESTEVAO, 273, 404, Jardim Leopoldina, Porto Alegre / RS, CEP 91240001 | H58: 180
A59: Contrato 308794 - HIPOLITO DA COSTA, 211, 301, Santa Tereza, Porto Alegre / RS, CEP 90840-110 | H59: 3024
A60: Devolução de Antecipação de Comissão - Contrato 308794 - HIPOLITO DA COSTA, 211, 301, Santa Tereza, Porto Alegre / RS, CEP 90840-110 | H60: -1700.7
A61: Contrato 236686 - CT 12867 - Avenida Assis Brasil 1720 apto 401 - IMOVEL MKTPLACE | H61: 4766.45
A67: TRANSFERÊNCIA DO PIPEIMOBI PARA CAIXA
A69: Transferência para Goethe Imóveis Ltda. | B69: -4006.34
A70: Transferência para Goethe Imóveis Ltda. | B70: -3346.4
A71: Transferência para GOETHE IMOVEIS LTDA (CPF/CNPJ 17194329000133) | B71: -3000
A72: Transferência para Goethe Imóveis Ltda. | E72: -5000
A73: Transferência para Goethe Imóveis Ltda. | E73: -2539.21
A74: Transferência para Goethe Imóveis Ltda. | H74: -2741.06
A80: TOTAL FATURAMENTO | B80: =SUM(B2:B79) -> 81913.06 | E80: =SUM(E2:E79) -> 38410.4 | H80: =SUM(H2:H79) -> 14472.65 | K80: =SUM(K2:K79) -> 0 | N80: =SUM(N2:N79) -> 0 | Q80: =SUM(Q2:Q79) -> 0 | T80: =SUM(T2:T79) -> 0 | W80: =SUM(W2:W79) -> 0 | Z80: =SUM(Z2:Z79) -> 0 | AC80: =SUM(AC2:AC79) -> 0 | AF80: =SUM(AF2:AF79) -> 0 | AI80: =SUM(AI2:AI79) -> 0
A82: DESPESAS OPERACIONAIS DO PIPEIMOB
A83: Liquidação de Cobrança (boleto) | B83: 30 | E83: 25 | H83: 5
A84: Liquidação de Cobrança (PIX QR Code) | E84: 10
A85: Fee Transacional (franqueadora) | B85: 168 | E85: 168 | H85: 42
A87: TOTAL DESPESAS OPERACIONAIS DO PIPEIMOB | B87: =SUM(B83:B86) -> 198 | C87: =SUM(C83:C86) -> 0 | D87: =SUM(D83:D86) -> 0 | E87: =SUM(E83:E86) -> 203 | F87: =SUM(F83:F86) -> 0 | G87: =SUM(G83:G86) -> 0 | H87: =SUM(H83:H86) -> 47 | I87: =SUM(I83:I86) -> 0 | ... AI87: =SUM(AI83:AI86) -> 0
A89: TRANSFERÊNCIAS
A91: TRANSFERÊNCIAS PELA CAIXA
A93: Reembolsode custos de transporte a cliente Manoela de Souza Dalabona | B93: 509.9
A94: Repasse do ato do contrato 189591 - Praia e Belas 1762 106 - Cleiton | B94: 20000
A95: Agenciamento Ag. Zona Norte - 768258 | E95: 170
A96: Agenciadora Bruna Kaeline - Agenciamento 759847 | E96: 6732
A103: TRANSFERÊNCIAS PELO PIPEIMOBI
A105: Diferença da comissão Luci Bortolanza Contrato Doutor Possidonio Cunha 719 Casa 2 | B105: 1207
A106: Transferência para o Pipeimob ???????????????????????????? | E106: 3426.72
A117: TOTAL TRANSFERÊNCIA | B117: =SUM(B89:B116) -> 21716.9 | E117: =SUM(E89:E116) -> 10328.72 | H117: =SUM(H89:H116) -> 0 | K117: =SUM(K89:K116) -> 0 | N117: =SUM(N89:N116) -> 0 | Q117: =SUM(Q89:Q116) -> 0 | T117: =SUM(T89:T116) -> 0 | W117: =SUM(W89:W116) -> 0 | Z117: =SUM(Z89:Z116) -> 0 | AC117: =SUM(AC89:AC116) -> 0 | AF117: =SUM(AF89:AF116) -> 0 | AI117: =SUM(AI89:AI116) -> 0
A119: ROYALTY
A121: ROYALTY
A127: ROYALTY PAGO PELO PIPEIMOB
A129: Royalty 462786 | B129: 1362
A130: Royalty 750147 | B130: 3634.05
A131: Royalty 147120 | B131: 2970
A132: Royalty 876859 | B132: 660
A133: Royalty 474600 | B133: 192.5
A134: Royalty 448520 | B134: 381.06
A135: Royalty 712267 | B135: 1320
A136: Royalty 760910 | B136: 957
A137: Royalty 722551 Parte 1 de 2 | B137: 1947
A138: Royalty 722551 Parte 2 de 2 | B138: 1947
A139: Royalty 415673 | E139: 4125
A140: Royalty 448520 | E140: 596.02
A141: Royalty 474600 | E141: 192.5
A142: Royalty 495832 | E142: 1320
A143: Royalty 748245 | E143: 2805
A144: Royalty 759002 | E144: 1320
A145: Royalty 759847 | E145: 4356
A146: Royalty 308794 | H146: 950.4
A147: Royalty 236686 | H147: 832.24
A152: TOTAL ROYALTY | B152: =SUM(B119:B151) -> 15370.61 | E152: =SUM(E119:E151) -> 14714.52 | H152: =SUM(H119:H151) -> 1782.64 | K152: =SUM(K119:K151) -> 0 | N152: =SUM(N119:N151) -> 0 | Q152: =SUM(Q119:Q151) -> 0 | T152: =SUM(T119:T151) -> 0 | W152: =SUM(W119:W151) -> 0 | Z152: =SUM(Z119:Z151) -> 0 | AC152: =SUM(AC119:AC151) -> 0 | AF152: =SUM(AF119:AF151) -> 0 | AI152: =SUM(AI119:AI151) -> 0
A154: TOTAL FATURAMENTO LÍQUIDO VENDAS | B154: =B80-B87-B117-B152 -> 44627.55 | C154: =C80-C87-C117-C152 -> 0 | D154: =D80-D87-D117-D152 -> 0 | E154: =E80-E87-E117-E152 -> 13164.16 | F154: =F80-F87-F117-F152 -> 0 | G154: =G80-G87-G117-G152 -> 0 | H154: =H80-H87-H117-H152 -> 12643.01 | I154: =I80-I87-I117-I152 -> 0 | ... AI154: =AI80-AI87-AI117-AI152 -> 0
A157: FATURAMENTO ALUGUEL CLIENTE
A159: NFSe - 399 - 474 2025 - Contrato 81136536 - RUA SILVA SÓ 183 APTO 203 | B159: 1400
A160: NFSe - 398 - 472 2025 - Contrato 81135389 - RUA ANDRADAS, DOS 487 APTO 704 | B160: 420
A161: NFSe - 403 - 482 2025 - Contrato 81136259 - RUA DONA AUGUSTA 427 APTO 308 | B161: 420
A162: NFSe - 407 - 490 2025 - Contrato 81136245 - RUA RUA TITO LÍVIO ZAMBECARI 408 APTO 602 BOX 01 | B162: 2618
A163: NFSe - 404 - 484 2025 - Contrato 81136461 - RUA GENERAL SALUSTIANO 330 APTO 507 | B163: 1580
A164: NFSe - 397 - 470 2025 - Contrato 81128565 - RUA EDMUNDO BASTIAN 238 APTO 401 BOX:8 | B164: 674.33
A165: NFSe - 396 - 468 2025 - Contrato 81136319 - AVENIDA GUAPORÉ 560 APTO 203 | B165: 875
...

Sheet DESPESAS
B1: 46023 | F1: 46054 | J1: 46082 | N1: 46113 | R1: 46143 | V1: 46174 | Z1: 46204 | AD1: 46235 | AH1: 46266 | AL1: 46296 | AP1: 46327 | AT1: 46357 | AX1: ACUMULADO 2026 | BB1: Rateio de Venda: | BC1: 100
B2: TOTAL | C2: VENDA | D2: ALUGUEL | E2: REFERÊNCIA | F2: TOTAL | G2: VENDA | H2: ALUGUEL | I2: REFERÊNCIA | J2: TOTAL | K2: VENDA | L2: ALUGUEL | M2: REFERÊNCIA | N2: TOTAL | O2: VENDA | P2: ALUGUEL | Q2: REFERÊNCIA | R2: TOTAL | S2: VENDA | T2: ALUGUEL | U2: REFERÊNCIA | V2: TOTAL | W2: VENDA | X2: ALUGUEL | Y2: REFERÊNCIA | Z2: TOTAL | AA2: VENDA | AB2: ALUGUEL | AC2: REFERÊNCIA | AD2: TOTAL | AE2: VENDA | AF2: ALUGUEL | AG2: REFERÊNCIA | AH2: TOTAL | AI2: VENDA | AJ2: ALUGUEL | AK2: REFERÊNCIA | AL2: TOTAL | AM2: VENDA | AN2: ALUGUEL | AO2: REFERÊNCIA | AP2: TOTAL | AQ2: VENDA | AR2: ALUGUEL | AS2: REFERÊNCIA | AT2: TOTAL | AU2: VENDA | AV2: ALUGUEL | AW2: REFERÊNCIA | AX2: TOTAL | AY2: VENDA | AZ2: ALUGUEL | BA2: VENDA | BB2: ALUGUEL | BC2: Valor do Rateio
A3: CONTAS DE CONSUMO
A4: GASTOS ESPAÇO FÍSICO
A5: Água Mineral | B5: =C5+D5 -> 0 | C5: =E5*$BA5/100 -> 0 | D5: =E5*$BB5/100 -> 0 | F5: =G5+H5 -> 0 | G5: =I5*$BA5/100 -> 0 | H5: =I5*$BB5/100 -> 0 | J5: =K5+L5 -> 0 | K5: =M5*$BA5/100 -> 0 | L5: =M5*$BB5/100 -> 0 | N5: =O5+P5 -> 0 | O5: =Q5*$BA5/100 -> 0 | P5: =Q5*$BB5/100 -> 0 | R5: =S5+T5 -> 0 | S5: =U5*$BA5/100 -> 0 | T5: =U5*$BB5/100 -> 0 | V5: =W5+X5 -> 0 | W5: =Y5*$BA5/100 -> 0 | X5: =Y5*$BB5/100 -> 0 | Z5: =AA5+AB5 -> 0 | AA5: =AC5*$BA5/100 -> 0 | AB5: =AC5*$BB5/100 -> 0 | AD5: =AE5+AF5 -> 0 | AE5: =AG5*$BA5/100 -> 0 | AF5: =AG5*$BB5/100 -> 0 | AH5: =AI5+AJ5 -> 0 | AI5: =AK5*$BA5/100 -> 0 | AJ5: =AK5*$BB5/100 -> 0 | AL5: =AM5+AN5 -> 0 | AM5: =AO5*$BA5/100 -> 0 | AN5: =AO5*$BB5/100 -> 0 | AP5: =AQ5+AR5 -> 0 | AQ5: =AS5*$BA5/100 -> 0 | AR5: =AS5*$BB5/100 -> 0 | AT5: =AU5+AV5 -> 0 | AU5: =AW5*$BA5/100 -> 0 | AV5: =AW5*$BB5/100 -> 0 | AX5: =B5+F5+J5+N5+R5+V5+Z5+AD5+AH5+AL5+AP5+AT5 -> 0 | AY5: =C5+G5+K5+O5+S5+W5+AA5+AE5+AI5+AM5+AQ5+AU5 -> 0 | AZ5: =D5+H5+L5+P5+T5+X5+AB5+AF5+AJ5+AN5+AR5+AV5 -> 0 | BA5: =BC$1 -> 100 | BB5: =100-BA5 -> 0 | BC5: =AX5*(BB5/100) -> 0 | BF5: CELULARES
A6: Aluguel /IPTU | B6: =C6+D6 -> 16946.5 | C6: =E6*$BA6/100 -> 16946.5 | D6: =E6*$BB6/100 -> 0 | E6: 16946.5 | F6: =G6+H6 -> 16715.19 | G6: =I6*$BA6/100 -> 16715.19 | H6: =I6*$BB6/100 -> 0 | I6: 16715.19 | J6: =K6+L6 -> 0 | K6: =M6*$BA6/100 -> 0 | L6: =M6*$BB6/100 -> 0 | N6: =O6+P6 -> 0 | O6: =Q6*$BA6/100 -> 0 | P6: =Q6*$BB6/100 -> 0 | R6: =S6+T6 -> 0 | S6: =U6*$BA6/100 -> 0 | T6: =U6*$BB6/100 -> 0 | V6: =W6+X6 -> 0 | W6: =Y6*$BA6/100 -> 0 | X6: =Y6*$BB6/100 -> 0 | Z6: =AA6+AB6 -> 0 | AA6: =AC6*$BA6/100 -> 0 | AB6: =AC6*$BB6/100 -> 0 | AD6: =AE6+AF6 -> 0 | AE6: =AG6*$BA6/100 -> 0 | AF6: =AG6*$BB6/100 -> 0 | AH6: =AI6+AJ6 -> 0 | AI6: =AK6*$BA6/100 -> 0 | AJ6: =AK6*$BB6/100 -> 0 | AL6: =AM6+AN6 -> 0 | AM6: =AO6*$BA6/100 -> 0 | AN6: =AO6*$BB6/100 -> 0 | AP6: =AQ6+AR6 -> 0 | AQ6: =AS6*$BA6/100 -> 0 | AR6: =AS6*$BB6/100 -> 0 | AT6: =AU6+AV6 -> 0 | AU6: =AW6*$BA6/100 -> 0 | AV6: =AW6*$BB6/100 -> 0 | AX6: =B6+F6+J6+N6+R6+V6+Z6+AD6+AH6+AL6+AP6+AT6 -> 33661.69 | AY6: =C6+G6+K6+O6+S6+W6+AA6+AE6+AI6+AM6+AQ6+AU6 -> 33661.69 | AZ6: =D6+H6+L6+P6+T6+X6+AB6+AF6+AJ6+AN6+AR6+AV6 -> 0 | BA6: =BC$1 -> 100 | BB6: =100-BA6 -> 0 | BC6: =AX6*(BB6/100) -> 0 | BF6: 1 | BG6: andressa
A7: Claro - celular | B7: =C7+D7 -> 293.38 | C7: =E7*$BA7/100 -> 0 | D7: =E7*$BB7/100 -> 293.38 | E7: 293.38 | F7: =G7+H7 -> 300.5 | G7: =I7*$BA7/100 -> 0 | H7: =I7*$BB7/100 -> 300.5 | I7: 300.5 | J7: =K7+L7 -> 392.24 | K7: =M7*$BA7/100 -> 0 | L7: =M7*$BB7/100 -> 392.24 | M7: 392.24 | N7: =O7+P7 -> 0 | O7: =Q7*$BA7/100 -> 0 | P7: =Q7*$BB7/100 -> 0 | R7: =S7+T7 -> 0 | S7: =U7*$BA7/100 -> 0 | T7: =U7*$BB7/100 -> 0 | V7: =W7+X7 -> 0 | W7: =Y7*$BA7/100 -> 0 | X7: =Y7*$BB7/100 -> 0 | Z7: =AA7+AB7 -> 0 | AA7: =AC7*$BA7/100 -> 0 | AB7: =AC7*$BB7/100 -> 0 | AD7: =AE7+AF7 -> 0 | AE7: =AG7*$BA7/100 -> 0 | AF7: =AG7*$BB7/100 -> 0 | AH7: =AI7+AJ7 -> 0 | AI7: =AK7*$BA7/100 -> 0 | AJ7: =AK7*$BB7/100 -> 0 | AL7: =AM7+AN7 -> 0 | AM7: =AO7*$BA7/100 -> 0 | AN7: =AO7*$BB7/100 -> 0 | AP7: =AQ7+AR7 -> 0 | AQ7: =AS7*$BA7/100 -> 0 | AR7: =AS7*$BB7/100 -> 0 | AT7: =AU7+AV7 -> 0 | AU7: =AW7*$BA7/100 -> 0 | AV7: =AW7*$BB7/100 -> 0 | AX7: =B7+F7+J7+N7+R7+V7+Z7+AD7+AH7+AL7+AP7+AT7 -> 986.12 | AY7: =C7+G7+K7+O7+S7+W7+AA7+AE7+AI7+AM7+AQ7+AU7 -> 0 | AZ7: =D7+H7+L7+P7+T7+X7+AB7+AF7+AJ7+AN7+AR7+AV7 -> 986.12 | BA7: 0 | BB7: =100-BA7 -> 100 | BF7: 1 | BG7: douglas
A8: Contabilidade | B8: =C8+D8 -> 350 | C8: =E8*$BA8/100 -> 350 | D8: =E8*$BB8/100 -> 0 | E8: 350 | F8: =G8+H8 -> 350 | G8: =I8*$BA8/100 -> 350 | H8: =I8*$BB8/100 -> 0 | I8: 350 | J8: =K8+L8 -> 0 | K8: =M8*$BA8/100 -> 0 | L8: =M8*$BB8/100 -> 0 | N8: =O8+P8 -> 0 | O8: =Q8*$BA8/100 -> 0 | P8: =Q8*$BB8/100 -> 0 | R8: =S8+T8 -> 0 | S8: =U8*$BA8/100 -> 0 | T8: =U8*$BB8/100 -> 0 | V8: =W8+X8 -> 0 | W8: =Y8*$BA8/100 -> 0 | X8: =Y8*$BB8/100 -> 0 | Z8: =AA8+AB8 -> 0 | AA8: =AC8*$BA8/100 -> 0 | AB8: =AC8*$BB8/100 -> 0 | AD8: =AE8+AF8 -> 0 | AE8: =AG8*$BA8/100 -> 0 | AF8: =AG8*$BB8/100 -> 0 | AH8: =AI8+AJ8 -> 0 | AI8: =AK8*$BA8/100 -> 0 | AJ8: =AK8*$BB8/100 -> 0 | AL8: =AM8+AN8 -> 0 | AM8: =AO8*$BA8/100 -> 0 | AN8: =AO8*$BB8/100 -> 0 | AP8: =AQ8+AR8 -> 0 | AQ8: =AS8*$BA8/100 -> 0 | AR8: =AS8*$BB8/100 -> 0 | AT8: =AU8+AV8 -> 0 | AU8: =AW8*$BA8/100 -> 0 | AV8: =AW8*$BB8/100 -> 0 | AX8: =B8+F8+J8+N8+R8+V8+Z8+AD8+AH8+AL8+AP8+AT8 -> 700 | AY8: =C8+G8+K8+O8+S8+W8+AA8+AE8+AI8+AM8+AQ8+AU8 -> 700 | AZ8: =D8+H8+L8+P8+T8+X8+AB8+AF8+AJ8+AN8+AR8+AV8 -> 0 | BA8: =BC$1 -> 100 | BB8: =100-BA8 -> 0 | BC8: =AX8*(BB8/100) -> 0 | BF8: 1 | BG8: recepção
A9: Extintores | B9: =C9+D9 -> 0 | C9: =E9*$BA9/100 -> 0 | D9: =E9*$BB9/100 -> 0 | F9: =G9+H9 -> 0 | G9: =I9*$BA9/100 -> 0 | H9: =I9*$BB9/100 -> 0 | J9: =K9+L9 -> 0 | K9: =M9*$BA9/100 -> 0 | L9: =M9*$BB9/100 -> 0 | N9: =O9+P9 -> 0 | O9: =Q9*$BA9/100 -> 0 | P9: =Q9*$BB9/100 -> 0 | R9: =S9+T9 -> 0 | S9: =U9*$BA9/100 -> 0 | T9: =U9*$BB9/100 -> 0 | V9: =W9+X9 -> 0 | W9: =Y9*$BA9/100 -> 0 | X9: =Y9*$BB9/100 -> 0 | Z9: =AA9+AB9 -> 0 | AA9: =AC9*$BA9/100 -> 0 | AB9: =AC9*$BB9/100 -> 0 | AD9: =AE9+AF9 -> 0 | AE9: =AG9*$BA9/100 -> 0 | AF9: =AG9*$BB9/100 -> 0 | AH9: =AI9+AJ9 -> 0 | AI9: =AK9*$BA9/100 -> 0 | AJ9: =AK9*$BB9/100 -> 0 | AL9: =AM9+AN9 -> 0 | AM9: =AO9*$BA9/100 -> 0 | AN9: =AO9*$BB9/100 -> 0 | AP9: =AQ9+AR9 -> 0 | AQ9: =AS9*$BA9/100 -> 0 | AR9: =AS9*$BB9/100 -> 0 | AT9: =AU9+AV9 -> 0 | AU9: =AW9*$BA9/100 -> 0 | AV9: =AW9*$BB9/100 -> 0 | AX9: =B9+F9+J9+N9+R9+V9+Z9+AD9+AH9+AL9+AP9+AT9 -> 0 | AY9: =C9+G9+K9+O9+S9+W9+AA9+AE9+AI9+AM9+AQ9+AU9 -> 0 | AZ9: =D9+H9+L9+P9+T9+X9+AB9+AF9+AJ9+AN9+AR9+AV9 -> 0 | BA9: =BC$1 -> 100 | BB9: =100-BA9 -> 0 | BC9: =AX9*(BB9/100) -> 0 | BF9: 1 | BG9: jonas
A10: Informática | B10: =C10+D10 -> 0 | C10: =E10*$BA10/100 -> 0 | D10: =E10*$BB10/100 -> 0 | F10: =G10+H10 -> 270 | G10: =I10*$BA10/100 -> 270 | H10: =I10*$BB10/100 -> 0 | I10: 270 | J10: =K10+L10 -> 0 | K10: =M10*$BA10/100 -> 0 | L10: =M10*$BB10/100 -> 0 | N10: =O10+P10 -> 0 | O10: =Q10*$BA10/100 -> 0 | P10: =Q10*$BB10/100 -> 0 | R10: =S10+T10 -> 0 | S10: =U10*$BA10/100 -> 0 | T10: =U10*$BB10/100 -> 0 | V10: =W10+X10 -> 0 | W10: =Y10*$BA10/100 -> 0 | X10: =Y10*$BB10/100 -> 0 | Z10: =AA10+AB10 -> 0 | AA10: =AC10*$BA10/100 -> 0 | AB10: =AC10*$BB10/100 -> 0 | AD10: =AE10+AF10 -> 0 | AE10: =AG10*$BA10/100 -> 0 | AF10: =AG10*$BB10/100 -> 0 | AH10: =AI10+AJ10 -> 0 | AI10: =AK10*$BA10/100 -> 0 | AJ10: =AK10*$BB10/100 -> 0 | AL10: =AM10+AN10 -> 0 | AM10: =AO10*$BA10/100 -> 0 | AN10: =AO10*$BB10/100 -> 0 | AP10: =AQ10+AR10 -> 0 | AQ10: =AS10*$BA10/100 -> 0 | AR10: =AS10*$BB10/100 -> 0 | AT10: =AU10+AV10 -> 0 | AU10: =AW10*$BA10/100 -> 0 | AV10: =AW10*$BB10/100 -> 0 | AX10: =B10+F10+J10+N10+R10+V10+Z10+AD10+AH10+AL10+AP10+AT10 -> 270 | AY10: =C10+G10+K10+O10+S10+W10+AA10+AE10+AI10+AM10+AQ10+AU10 -> 270 | AZ10: =D10+H10+L10+P10+T10+X10+AB10+AF10+AJ10+AN10+AR10+AV10 -> 0 | BA10: =BC$1 -> 100 | BB10: =100-BA10 -> 0 | BC10: =AX10*(BB10/100) -> 0
A11: Limpeza da Loja | B11: =C11+D11 -> 1350 | C11: =E11*$BA11/100 -> 1350 | D11: =E11*$BB11/100 -> 0 | E11: =450+450+450 -> 1350 | F11: =G11+H11 -> 1350 | G11: =I11*$BA11/100 -> 1350 | H11: =I11*$BB11/100 -> 0 | I11: =450+300+150+450 -> 1350 | J11: =K11+L11 -> 1200 | K11: =M11*$BA11/100 -> 1200 | L11: =M11*$BB11/100 -> 0 | M11: =450+300+450 -> 1200 | N11: =O11+P11 -> 0 | O11: =Q11*$BA11/100 -> 0 | P11: =Q11*$BB11/100 -> 0 | R11: =S11+T11 -> 0 | S11: =U11*$BA11/100 -> 0 | T11: =U11*$BB11/100 -> 0 | V11: =W11+X11 -> 0 | W11: =Y11*$BA11/100 -> 0 | X11: =Y11*$BB11/100 -> 0 | Z11: =AA11+AB11 -> 0 | AA11: =AC11*$BA11/100 -> 0 | AB11: =AC11*$BB11/100 -> 0 | AD11: =AE11+AF11 -> 0 | AE11: =AG11*$BA11/100 -> 0 | AF11: =AG11*$BB11/100 -> 0 | AH11: =AI11+AJ11 -> 0 | AI11: =AK11*$BA11/100 -> 0 | AJ11: =AK11*$BB11/100 -> 0 | AL11: =AM11+AN11 -> 0 | AM11: =AO11*$BA11/100 -> 0 | AN11: =AO11*$BB11/100 -> 0 | AP11: =AQ11+AR11 -> 0 | AQ11: =AS11*$BA11/100 -> 0 | AR11: =AS11*$BB11/100 -> 0 | AT11: =AU11+AV11 -> 0 | AU11: =AW11*$BA11/100 -> 0 | AV11: =AW11*$BB11/100 -> 0 | AX11: =B11+F11+J11+N11+R11+V11+Z11+AD11+AH11+AL11+AP11+AT11 -> 3900 | AY11: =C11+G11+K11+O11+S11+W11+AA11+AE11+AI11+AM11+AQ11+AU11 -> 3900 | AZ11: =D11+H11+L11+P11+T11+X11+AB11+AF11+AJ11+AN11+AR11+AV11 -> 0 | BA11: =BC$1 -> 100 | BB11: =100-BA11 -> 0 | BC11: =AX11*(BB11/100) -> 0
A12: Algar - telefone fixo e internet | B12: =C12+D12 -> 0 | C12: =E12*$BA12/100 -> 0 | D12: =E12*$BB12/100 -> 0 | F12: =G12+H12 -> 203.43 | G12: =I12*$BA12/100 -> 203.43 | H12: =I12*$BB12/100 -> 0 | I12: 203.43 | J12: =K12+L12 -> 205.39 | K12: =M12*$BA12/100 -> 205.39 | L12: =M12*$BB12/100 -> 0 | M12: 205.39 | N12: =O12+P12 -> 0 | O12: =Q12*$BA12/100 -> 0 | P12: =Q12*$BB12/100 -> 0 | R12: =S12+T12 -> 0 | S12: =U12*$BA12/100 -> 0 | T12: =U12*$BB12/100 -> 0 | V12: =W12+X12 -> 0 | W12: =Y12*$BA12/100 -> 0 | X12: =Y12*$BB12/100 -> 0 | Z12: =AA12+AB12 -> 0 | AA12: =AC12*$BA12/100 -> 0 | AB12: =AC12*$BB12/100 -> 0 | AD12: =AE12+AF12 -> 0 | AE12: =AG12*$BA12/100 -> 0 | AF12: =AG12*$BB12/100 -> 0 | AH12: =AI12+AJ12 -> 0 | AI12: =AK12*$BA12/100 -> 0 | AJ12: =AK12*$BB12/100 -> 0 | AL12: =AM12+AN12 -> 0 | AM12: =AO12*$BA12/100 -> 0 | AN12: =AO12*$BB12/100 -> 0 | AP12: =AQ12+AR12 -> 0 | AQ12: =AS12*$BA12/100 -> 0 | AR12: =AS12*$BB12/100 -> 0 | AT12: =AU12+AV12 -> 0 | AU12: =AW12*$BA12/100 -> 0 | AV12: =AW12*$BB12/100 -> 0 | AX12: =B12+F12+J12+N12+R12+V12+Z12+AD12+AH12+AL12+AP12+AT12 -> 408.82 | AY12: =C12+G12+K12+O12+S12+W12+AA12+AE12+AI12+AM12+AQ12+AU12 -> 408.82 | AZ12: =D12+H12+L12+P12+T12+X12+AB12+AF12+AJ12+AN12+AR12+AV12 -> 0 | BA12: =BC$1 -> 100 | BB12: =100-BA12 -> 0 | BC12: =AX12*(BB12/100) -> 0
A13: ENERGIA | B13: =C13+D13 -> 1134.25 | C13: =E13*$BA13/100 -> 1134.25 | D13: =E13*$BB13/100 -> 0 | E13: 1134.25 | F13: =G13+H13 -> 0 | G13: =I13*$BA13/100 -> 0 | H13: =I13*$BB13/100 -> 0 | J13: =K13+L13 -> 1171.98 | K13: =M13*$BA13/100 -> 1171.98 | L13: =M13*$BB13/100 -> 0 | M13: 1171.98 | N13: =O13+P13 -> 0 | O13: =Q13*$BA13/100 -> 0 | P13: =Q13*$BB13/100 -> 0 | R13: =S13+T13 -> 0 | S13: =U13*$BA13/100 -> 0 | T13: =U13*$BB13/100 -> 0 | V13: =W13+X13 -> 0 | W13: =Y13*$BA13/100 -> 0 | X13: =Y13*$BB13/100 -> 0 | Z13: =AA13+AB13 -> 0 | AA13: =AC13*$BA13/100 -> 0 | AB13: =AC13*$BB13/100 -> 0 | AD13: =AE13+AF13 -> 0 | AE13: =AG13*$BA13/100 -> 0 | AF13: =AG13*$BB13/100 -> 0 | AH13: =AI13+AJ13 -> 0 | AI13: =AK13*$BA13/100 -> 0 | AJ13: =AK13*$BB13/100 -> 0 | AL13: =AM13+AN13 -> 0 | AM13: =AO13*$BA13/100 -> 0 | AN13: =AO13*$BB13/100 -> 0 | AP13: =AQ13+AR13 -> 0 | AQ13: =AS13*$BA13/100 -> 0 | AR13: =AS13*$BB13/100 -> 0 | AT13: =AU13+AV13 -> 0 | AU13: =AW13*$BA13/100 -> 0 | AV13: =AW13*$BB13/100 -> 0 | AX13: =B13+F13+J13+N13+R13+V13+Z13+AD13+AH13+AL13+AP13+AT13 -> 2306.23 | AY13: =C13+G13+K13+O13+S13+W13+AA13+AE13+AI13+AM13+AQ13+AU13 -> 2306.23 | AZ13: =D13+H13+L13+P13+T13+X13+AB13+AF13+AJ13+AN13+AR13+AV13 -> 0 | BA13: =BC$1 -> 100 | BB13: =100-BA13 -> 0 | BC13: =AX13*(BB13/100) -> 0
A14: Segurança SP | B14: =C14+D14 -> 0 | C14: =E14*$BA14/100 -> 0 | D14: =E14*$BB14/100 -> 0 | F14: =G14+H14 -> 361.86 | G14: =I14*$BA14/100 -> 361.86 | H14: =I14*$BB14/100 -> 0 | I14: =176.39+185.47 -> 361.86 | J14: =K14+L14 -> 0 | K14: =M14*$BA14/100 -> 0 | L14: =M14*$BB14/100 -> 0 | N14: =O14+P14 -> 0 | O14: =Q14*$BA14/100 -> 0 | P14: =Q14*$BB14/100 -> 0 | R14: =S14+T14 -> 0 | S14: =U14*$BA14/100 -> 0 | T14: =U14*$BB14/100 -> 0 | V14: =W14+X14 -> 0 | W14: =Y14*$BA14/100 -> 0 | X14: =Y14*$BB14/100 -> 0 | Z14: =AA14+AB14 -> 0 | AA14: =AC14*$BA14/100 -> 0 | AB14: =AC14*$BB14/100 -> 0 | AD14: =AE14+AF14 -> 0 | AE14: =AG14*$BA14/100 -> 0 | AF14: =AG14*$BB14/100 -> 0 | AH14: =AI14+AJ14 -> 0 | AI14: =AK14*$BA14/100 -> 0 | AJ14: =AK14*$BB14/100 -> 0 | AL14: =AM14+AN14 -> 0 | AM14: =AO14*$BA14/100 -> 0 | AN14: =AO14*$BB14/100 -> 0 | AP14: =AQ14+AR14 -> 0 | AQ14: =AS14*$BA14/100 -> 0 | AR14: =AS14*$BB14/100 -> 0 | AT14: =AU14+AV14 -> 0 | AU14: =AW14*$BA14/100 -> 0 | AV14: =AW14*$BB14/100 -> 0 | AX14: =B14+F14+J14+N14+R14+V14+Z14+AD14+AH14+AL14+AP14+AT14 -> 361.86 | AY14: =C14+G14+K14+O14+S14+W14+AA14+AE14+AI14+AM14+AQ14+AU14 -> 361.86 | AZ14: =D14+H14+L14+P14+T14+X14+AB14+AF14+AJ14+AN14+AR14+AV14 -> 0 | BA14: =BC$1 -> 100 | BB14: =100-BA14 -> 0 | BC14: =AX14*(BB14/100) -> 0
A15: TOTAL | B15: =SUM(B5:B14) -> 20074.13 | C15: =SUM(C5:C14) -> 19780.75 | D15: =SUM(D5:D14) -> 293.38 | E15: =SUM(E5:E14) -> 20074.13 | F15: =SUM(F5:F14) -> 19550.98 | G15: =SUM(G5:G14) -> 19250.48 | H15: =SUM(H5:H14) -> 300.5 | I15: =SUM(I5:I14) -> 19550.98 | ... AW15: =SUM(AW5:AW14) -> 0 | AX15: =B15+F15+J15+N15+R15+V15+Z15+AD15+AH15+AL15+AP15+AT15 -> 42594.72 | AY15: =C15+G15+K15+O15+S15+W15+AA15+AE15+AI15+AM15+AQ15+AU15 -> 41608.6 | AZ15: =D15+H15+L15+P15+T15+X15+AB15+AF15+AJ15+AN15+AR15+AV15 -> 986.12 | BC15: =SUM(BC4:BC14) -> 0
A16: MATERIAL
A17: Mantimentos | B17: =C17+D17 -> 0 | C17: =E17*$BA17/100 -> 0 | D17: =E17*$BB17/100 -> 0 | F17: =G17+H17 -> 0 | G17: =I17*$BA17/100 -> 0 | H17: =I17*$BB17/100 -> 0 | J17: =K17+L17 -> 905.03 | K17: =M17*$BA17/100 -> 905.03 | L17: =M17*$BB17/100 -> 0 | M17: 905.03 | N17: =O17+P17 -> 0 | O17: =Q17*$BA17/100 -> 0 | P17: =Q17*$BB17/100 -> 0 | R17: =S17+T17 -> 0 | S17: =U17*$BA17/100 -> 0 | T17: =U17*$BB17/100 -> 0 | V17: =W17+X17 -> 0 | W17: =Y17*$BA17/100 -> 0 | X17: =Y17*$BB17/100 -> 0 | Z17: =AA17+AB17 -> 0 | AA17: =AC17*$BA17/100 -> 0 | AB17: =AC17*$BB17/100 -> 0 | AD17: =AE17+AF17 -> 0 | AE17: =AG17*$BA17/100 -> 0 | AF17: =AG17*$BB17/100 -> 0 | AH17: =AI17+AJ17 -> 0 | AI17: =AK17*$BA17/100 -> 0 | AJ17: =AK17*$BB17/100 -> 0 | AL17: =AM17+AN17 -> 0 | AM17: =AO17*$BA17/100 -> 0 | AN17: =AO17*$BB17/100 -> 0 | AP17: =AQ17+AR17 -> 0 | AQ17: =AS17*$BA17/100 -> 0 | AR17: =AS17*$BB17/100 -> 0 | AT17: =AU17+AV17 -> 0 | AU17: =AW17*$BA17/100 -> 0 | AV17: =AW17*$BB17/100 -> 0 | AX17: =B17+F17+J17+N17+R17+V17+Z17+AD17+AH17+AL17+AP17+AT17 -> 905.03 | AY17: =C17+G17+K17+O17+S17+W17+AA17+AE17+AI17+AM17+AQ17+AU17 -> 905.03 | AZ17: =D17+H17+L17+P17+T17+X17+AB17+AF17+AJ17+AN17+AR17+AV17 -> 0 | BA17: =BC$1 -> 100 | BB17: =100-BA17 -> 0 | BC17: =AX17*(BB17/100) -> 0
A18: Material de limpeza | B18: =C18+D18 -> 0 | C18: =E18*$BA18/100 -> 0 | D18: =E18*$BB18/100 -> 0 | F18: =G18+H18 -> 0 | G18: =I18*$BA18/100 -> 0 | H18: =I18*$BB18/100 -> 0 | J18: =K18+L18 -> 0 | K18: =M18*$BA18/100 -> 0 | L18: =M18*$BB18/100 -> 0 | N18: =O18+P18 -> 0 | O18: =Q18*$BA18/100 -> 0 | P18: =Q18*$BB18/100 -> 0 | R18: =S18+T18 -> 0 | S18: =U18*$BA18/100 -> 0 | T18: =U18*$BB18/100 -> 0 | V18: =W18+X18 -> 0 | W18: =Y18*$BA18/100 -> 0 | X18: =Y18*$BB18/100 -> 0 | Z18: =AA18+AB18 -> 0 | AA18: =AC18*$BA18/100 -> 0 | AB18: =AC18*$BB18/100 -> 0 | AD18: =AE18+AF18 -> 0 | AE18: =AG18*$BA18/100 -> 0 | AF18: =AG18*$BB18/100 -> 0 | AH18: =AI18+AJ18 -> 0 | AI18: =AK18*$BA18/100 -> 0 | AJ18: =AK18*$BB18/100 -> 0 | AL18: =AM18+AN18 -> 0 | AM18: =AO18*$BA18/100 -> 0 | AN18: =AO18*$BB18/100 -> 0 | AP18: =AQ18+AR18 -> 0 | AQ18: =AS18*$BA18/100 -> 0 | AR18: =AS18*$BB18/100 -> 0 | AT18: =AU18+AV18 -> 0 | AU18: =AW18*$BA18/100 -> 0 | AV18: =AW18*$BB18/100 -> 0 | AX18: =B18+F18+J18+N18+R18+V18+Z18+AD18+AH18+AL18+AP18+AT18 -> 0 | AY18: =C18+G18+K18+O18+S18+W18+AA18+AE18+AI18+AM18+AQ18+AU18 -> 0 | AZ18: =D18+H18+L18+P18+T18+X18+AB18+AF18+AJ18+AN18+AR18+AV18 -> 0 | BA18: =BC$1 -> 100 | BB18: =100-BA18 -> 0 | BC18: =AX18*(BB18/100) -> 0
A19: Material de escritório | B19: =C19+D19 -> 200.7 | C19: =E19*$BA19/100 -> 200.7 | D19: =E19*$BB19/100 -> 0 | E19: 200.7 | F19: =G19+H19 -> 0 | G19: =I19*$BA19/100 -> 0 | H19: =I19*$BB19/100 -> 0 | J19: =K19+L19 -> 0 | K19: =M19*$BA19/100 -> 0 | L19: =M19*$BB19/100 -> 0 | N19: =O19+P19 -> 0 | O19: =Q19*$BA19/100 -> 0 | P19: =Q19*$BB19/100 -> 0 | R19: =S19+T19 -> 0 | S19: =U19*$BA19/100 -> 0 | T19: =U19*$BB19/100 -> 0 | V19: =W19+X19 -> 0 | W19: =Y19*$BA19/100 -> 0 | X19: =Y19*$BB19/100 -> 0 | Z19: =AA19+AB19 -> 0 | AA19: =AC19*$BA19/100 -> 0 | AB19: =AC19*$BB19/100 -> 0 | AD19: =AE19+AF19 -> 0 | AE19: =AG19*$BA19/100 -> 0 | AF19: =AG19*$BB19/100 -> 0 | AH19: =AI19+AJ19 -> 0 | AI19: =AK19*$BA19/100 -> 0 | AJ19: =AK19*$BB19/100 -> 0 | AL19: =AM19+AN19 -> 0 | AM19: =AO19*$BA19/100 -> 0 | AN19: =AO19*$BB19/100 -> 0 | AP19: =AQ19+AR19 -> 0 | AQ19: =AS19*$BA19/100 -> 0 | AR19: =AS19*$BB19/100 -> 0 | AT19: =AU19+AV19 -> 0 | AU19: =AW19*$BA19/100 -> 0 | AV19: =AW19*$BB19/100 -> 0 | AX19: =B19+F19+J19+N19+R19+V19+Z19+AD19+AH19+AL19+AP19+AT19 -> 200.7 | AY19: =C19+G19+K19+O19+S19+W19+AA19+AE19+AI19+AM19+AQ19+AU19 -> 200.7 | AZ19: =D19+H19+L19+P19+T19+X19+AB19+AF19+AJ19+AN19+AR19+AV19 -> 0 | BA19: =BC$1 -> 100 | BB19: =100-BA19 -> 0 | BC19: =AX19*(BB19/100) -> 0
A20: TOTAL | B20: =SUM(B17:B19) -> 200.7 | C20: =SUM(C17:C19) -> 200.7 | D20: =SUM(D17:D19) -> 0 | E20: =SUM(E17:E19) -> 200.7 | F20: =SUM(F17:F19) -> 0 | G20: =SUM(G17:G19) -> 0 | H20: =SUM(H17:H19) -> 0 | I20: =SUM(I17:I19) -> 0 | ... AW20: =SUM(AW17:AW19) -> 0 | AX20: =B20+F20+J20+N20+R20+V20+Z20+AD20+AH20+AL20+AP20+AT20 -> 1105.73 | AY20: =C20+G20+K20+O20+S20+W20+AA20+AE20+AI20+AM20+AQ20+AU20 -> 1105.73 | AZ20: =D20+H20+L20+P20+T20+X20+AB20+AF20+AJ20+AN20+AR20+AV20 -> 0 | BC20: =SUM(BC16:BC19) -> 0
A21: MANUTENÇÃO
A22: Manutenção | B22: =C22+D22 -> 0 | C22: =E22*$BA22/100 -> 0 | D22: =E22*$BB22/100 -> 0 | F22: =G22+H22 -> 0 | G22: =I22*$BA22/100 -> 0 | H22: =I22*$BB22/100 -> 0 | J22: =K22+L22 -> 0 | K22: =M22*$BA22/100 -> 0 | L22: =M22*$BB22/100 -> 0 | N22: =O22+P22 -> 0 | O22: =Q22*$BA22/100 -> 0 | P22: =Q22*$BB22/100 -> 0 | R22: =S22+T22 -> 0 | S22: =U22*$BA22/100 -> 0 | T22: =U22*$BB22/100 -> 0 | V22: =W22+X22 -> 0 | W22: =Y22*$BA22/100 -> 0 | X22: =Y22*$BB22/100 -> 0 | Z22: =AA22+AB22 -> 0 | AA22: =AC22*$BA22/100 -> 0 | AB22: =AC22*$BB22/100 -> 0 | AD22: =AE22+AF22 -> 0 | AE22: =AG22*$BA22/100 -> 0 | AF22: =AG22*$BB22/100 -> 0 | AH22: =AI22+AJ22 -> 0 | AI22: =AK22*$BA22/100 -> 0 | AJ22: =AK22*$BB22/100 -> 0 | AL22: =AM22+AN22 -> 0 | AM22: =AO22*$BA22/100 -> 0 | AN22: =AO22*$BB22/100 -> 0 | AP22: =AQ22+AR22 -> 0 | AQ22: =AS22*$BA22/100 -> 0 | AR22: =AS22*$BB22/100 -> 0 | AT22: =AU22+AV22 -> 0 | AU22: =AW22*$BA22/100 -> 0 | AV22: =AW22*$BB22/100 -> 0 | AX22: =B22+F22+J22+N22+R22+V22+Z22+AD22+AH22+AL22+AP22+AT22 -> 0 | AY22: =C22+G22+K22+O22+S22+W22+AA22+AE22+AI22+AM22+AQ22+AU22 -> 0 | AZ22: =D22+H22+L22+P22+T22+X22+AB22+AF22+AJ22+AN22+AR22+AV22 -> 0 | BA22: =BC$1 -> 100 | BB22: =100-BA22 -> 0 | BC22: =AX22*(BB22/100) -> 0
A23: Manutenção dos Ar condicionados | B23: =C23+D23 -> 960.64 | C23: =E23*$BA23/100 -> 960.64 | D23: =E23*$BB23/100 -> 0 | E23: =780.52+180.12 -> 960.64 | F23: =G23+H23 -> 180 | G23: =I23*$BA23/100 -> 180 | H23: =I23*$BB23/100 -> 0 | I23: 180 | J23: =K23+L23 -> 180 | K23: =M23*$BA23/100 -> 180 | L23: =M23*$BB23/100 -> 0 | M23: 180 | N23: =O23+P23 -> 0 | O23: =Q23*$BA23/100 -> 0 | P23: =Q23*$BB23/100 -> 0 | R23: =S23+T23 -> 0 | S23: =U23*$BA23/100 -> 0 | T23: =U23*$BB23/100 -> 0 | V23: =W23+X23 -> 0 | W23: =Y23*$BA23/100 -> 0 | X23: =Y23*$BB23/100 -> 0 | Z23: =AA23+AB23 -> 0 | AA23: =AC23*$BA23/100 -> 0 | AB23: =AC23*$BB23/100 -> 0 | AD23: =AE23+AF23 -> 0 | AE23: =AG23*$BA23/100 -> 0 | AF23: =AG23*$BB23/100 -> 0 | AH23: =AI23+AJ23 -> 0 | AI23: =AK23*$BA23/100 -> 0 | AJ23: =AK23*$BB23/100 -> 0 | AL23: =AM23+AN23 -> 0 | AM23: =AO23*$BA23/100 -> 0 | AN23: =AO23*$BB23/100 -> 0 | AP23: =AQ23+AR23 -> 0 | AQ23: =AS23*$BA23/100 -> 0 | AR23: =AS23*$BB23/100 -> 0 | AT23: =AU23+AV23 -> 0 | AU23: =AW23*$BA23/100 -> 0 | AV23: =AW23*$BB23/100 -> 0 | AX23: =B23+F23+J23+N23+R23+V23+Z23+AD23+AH23+AL23+AP23+AT23 -> 1320.64 | AY23: =C23+G23+K23+O23+S23+W23+AA23+AE23+AI23+AM23+AQ23+AU23 -> 1320.64 | AZ23: =D23+H23+L23+P23+T23+X23+AB23+AF23+AJ23+AN23+AR23+AV23 -> 0 | BA23: =BC$1 -> 100 | BB23: =100-BA23 -> 0 | BC23: =AX23*(BB23/100) -> 0
A24: Manutenção dos computadores | B24: =C24+D24 -> 0 | C24: =E24*$BA24/100 -> 0 | D24: =E24*$BB24/100 -> 0 | F24: =G24+H24 -> 0 | G24: =I24*$BA24/100 -> 0 | H24: =I24*$BB24/100 -> 0 | J24: =K24+L24 -> 0 | K24: =M24*$BA24/100 -> 0 | L24: =M24*$BB24/100 -> 0 | N24: =O24+P24 -> 0 | O24: =Q24*$BA24/100 -> 0 | P24: =Q24*$BB24/100 -> 0 | R24: =S24+T24 -> 0 | S24: =U24*$BA24/100 -> 0 | T24: =U24*$BB24/100 -> 0 | V24: =W24+X24 -> 0 | W24: =Y24*$BA24/100 -> 0 | X24: =Y24*$BB24/100 -> 0 | Z24: =AA24+AB24 -> 0 | AA24: =AC24*$BA24/100 -> 0 | AB24: =AC24*$BB24/100 -> 0 | AD24: =AE24+AF24 -> 0 | AE24: =AG24*$BA24/100 -> 0 | AF24: =AG24*$BB24/100 -> 0 | AH24: =AI24+AJ24 -> 0 | AI24: =AK24*$BA24/100 -> 0 | AJ24: =AK24*$BB24/100 -> 0 | AL24: =AM24+AN24 -> 0 | AM24: =AO24*$BA24/100 -> 0 | AN24: =AO24*$BB24/100 -> 0 | AP24: =AQ24+AR24 -> 0 | AQ24: =AS24*$BA24/100 -> 0 | AR24: =AS24*$BB24/100 -> 0 | AT24: =AU24+AV24 -> 0 | AU24: =AW24*$BA24/100 -> 0 | AV24: =AW24*$BB24/100 -> 0 | AX24: =B24+F24+J24+N24+R24+V24+Z24+AD24+AH24+AL24+AP24+AT24 -> 0 | AY24: =C24+G24+K24+O24+S24+W24+AA24+AE24+AI24+AM24+AQ24+AU24 -> 0 | AZ24: =D24+H24+L24+P24+T24+X24+AB24+AF24+AJ24+AN24+AR24+AV24 -> 0 | BA24: =BC$1 -> 100 | BB24: =100-BA24 -> 0 | BC24: =AX24*(BB24/100) -> 0
A25: Manutenção da Telefonia | B25: =C25+D25 -> 519.98 | C25: =E25*$BA25/100 -> 519.98 | D25: =E25*$BB25/100 -> 0 | E25: =460+59.98 -> 519.98 | F25: =G25+H25 -> 0 | G25: =I25*$BA25/100 -> 0 | H25: =I25*$BB25/100 -> 0 | J25: =K25+L25 -> 0 | K25: =M25*$BA25/100 -> 0 | L25: =M25*$BB25/100 -> 0 | N25: =O25+P25 -> 0 | O25: =Q25*$BA25/100 -> 0 | P25: =Q25*$BB25/100 -> 0 | R25: =S25+T25 -> 0 | S25: =U25*$BA25/100 -> 0 | T25: =U25*$BB25/100 -> 0 | V25: =W25+X25 -> 0 | W25: =Y25*$BA25/100 -> 0 | X25: =Y25*$BB25/100 -> 0 | Z25: =AA25+AB25 -> 0 | AA25: =AC25*$BA25/100 -> 0 | AB25: =AC25*$BB25/100 -> 0 | AD25: =AE25+AF25 -> 0 | AE25: =AG25*$BA25/100 -> 0 | AF25: =AG25*$BB25/100 -> 0 | AH25: =AI25+AJ25 -> 0 | AI25: =AK25*$BA25/100 -> 0 | AJ25: =AK25*$BB25/100 -> 0 | AL25: =AM25+AN25 -> 0 | AM25: =AO25*$BA25/100 -> 0 | AN25: =AO25*$BB25/100 -> 0 | AP25: =AQ25+AR25 -> 0 | AQ25: =AS25*$BA25/100 -> 0 | AR25: =AS25*$BB25/100 -> 0 | AT25: =AU25+AV25 -> 0 | AU25: =AW25*$BA25/100 -> 0 | AV25: =AW25*$BB25/100 -> 0 | AX25: =B25+F25+J25+N25+R25+V25+Z25+AD25+AH25+AL25+AP25+AT25 -> 519.98 | AY25: =C25+G25+K25+O25+S25+W25+AA25+AE25+AI25+AM25+AQ25+AU25 -> 519.98 | AZ25: =D25+H25+L25+P25+T25+X25+AB25+AF25+AJ25+AN25+AR25+AV25 -> 0 | BA25: =BC$1 -> 100 | BB25: =100-BA25 -> 0 | BC25: =AX25*(BB25/100) -> 0
A26: Outro | B26: =C26+D26 -> 0 | C26: =E26*$BA26/100 -> 0 | D26: =E26*$BB26/100 -> 0 | F26: =G26+H26 -> 0 | G26: =I26*$BA26/100 -> 0 | H26: =I26*$BB26/100 -> 0 | J26: =K26+L26 -> 0 | K26: =M26*$BA26/100 -> 0 | L26: =M26*$BB26/100 -> 0 | N26: =O26+P26 -> 0 | O26: =Q26*$BA26/100 -> 0 | P26: =Q26*$BB26/100 -> 0 | R26: =S26+T26 -> 0 | S26: =U26*$BA26/100 -> 0 | T26: =U26*$BB26/100 -> 0 | V26: =W26+X26 -> 0 | W26: =Y26*$BA26/100 -> 0 | X26: =Y26*$BB26/100 -> 0 | Z26: =AA26+AB26 -> 0 | AA26: =AC26*$BA26/100 -> 0 | AB26: =AC26*$BB26/100 -> 0 | AD26: =AE26+AF26 -> 0 | AE26: =AG26*$BA26/100 -> 0 | AF26: =AG26*$BB26/100 -> 0 | AH26: =AI26+AJ26 -> 0 | AI26: =AK26*$BA26/100 -> 0 | AJ26: =AK26*$BB26/100 -> 0 | AL26: =AM26+AN26 -> 0 | AM26: =AO26*$BA26/100 -> 0 | AN26: =AO26*$BB26/100 -> 0 | AP26: =AQ26+AR26 -> 0 | AQ26: =AS26*$BA26/100 -> 0 | AR26: =AS26*$BB26/100 -> 0 | AT26: =AU26+AV26 -> 0 | AU26: =AW26*$BA26/100 -> 0 | AV26: =AW26*$BB26/100 -> 0 | AX26: =B26+F26+J26+N26+R26+V26+Z26+AD26+AH26+AL26+AP26+AT26 -> 0 | AY26: =C26+G26+K26+O26+S26+W26+AA26+AE26+AI26+AM26+AQ26+AU26 -> 0 | AZ26: =D26+H26+L26+P26+T26+X26+AB26+AF26+AJ26+AN26+AR26+AV26 -> 0 | BA26: =BC$1 -> 100 | BB26: =100-BA26 -> 0 | BC26: =AX26*(BB26/100) -> 0
A27: TOTAL | B27: =SUM(B22:B26) -> 1480.62 | C27: =SUM(C22:C26) -> 1480.62 | D27: =SUM(D22:D26) -> 0 | E27: =SUM(E22:E26) -> 1480.62 | F27: =SUM(F22:F26) -> 180 | G27: =SUM(G22:G26) -> 180 | H27: =SUM(H22:H26) -> 0 | I27: =SUM(I22:I26) -> 180 | ... AW27: =SUM(AW22:AW26) -> 0 | AX27: =B27+F27+J27+N27+R27+V27+Z27+AD27+AH27+AL27+AP27+AT27 -> 1840.62 | AY27: =C27+G27+K27+O27+S27+W27+AA27+AE27+AI27+AM27+AQ27+AU27 -> 1840.62 | AZ27: =D27+H27+L27+P27+T27+X27+AB27+AF27+AJ27+AN27+AR27+AV27 -> 0 | BC27: =SUM(BC21:BC26) -> 0
A28: TOTAL CONTAS DE CONSUMO | B28: =B15+B20+B27 -> 21755.45 | C28: =C15+C20+C27 -> 21462.07 | D28: =D15+D20+D27 -> 293.38 | E28: =E15+E20+E27 -> 21755.45 | F28: =F15+F20+F27 -> 19730.98 | G28: =G15+G20+G27 -> 19430.48 | H28: =H15+H20+H27 -> 300.5 | I28: =I15+I20+I27 -> 19730.98 | ... AW28: =AW15+AW20+AW27 -> 0 | AX28: =B28+F28+J28+N28+R28+V28+Z28+AD28+AH28+AL28+AP28+AT28 -> 45541.07 | AY28: =C28+G28+K28+O28+S28+W28+AA28+AE28+AI28+AM28+AQ28+AU28 -> 44554.95 | AZ28: =D28+H28+L28+P28+T28+X28+AB28+AF28+AJ28+AN28+AR28+AV28 -> 986.12 | BC28: =BC15+BC20+BC27 -> 0
A29: CONTAS OPERACIONAIS VENDA
A30: ASSOCI | B30: =C30+D30 -> 0 | F30: =G30+H30 -> 0 | J30: =K30+L30 -> 0 | N30: =O30+P30 -> 0 | R30: =S30+T30 -> 0 | V30: =W30+X30 -> 0 | Z30: =AA30+AB30 -> 0 | AD30: =AE30+AF30 -> 0 | AH30: =AI30+AJ30 -> 0 | AL30: =AM30+AN30 -> 0 | AP30: =AQ30+AR30 -> 0 | AT30: =AU30+AV30 -> 0 | AX30: =B30+F30+J30+N30+R30+V30+Z30+AD30+AH30+AL30+AP30+AT30 -> 0 | AY30: =C30+G30+K30+O30+S30+W30+AA30+AE30+AI30+AM30+AQ30+AU30 -> 0 | AZ30: =D30+H30+L30+P30+T30+X30+AB30+AF30+AJ30+AN30+AR30+AV30 -> 0
A31: Ação de marketing / material de divulgação | B31: =C31+D31 -> 0 | F31: =G31+H31 -> 0 | J31: =K31+L31 -> 0 | N31: =O31+P31 -> 0 | R31: =S31+T31 -> 0 | V31: =W31+X31 -> 0 | Z31: =AA31+AB31 -> 0 | AD31: =AE31+AF31 -> 0 | AH31: =AI31+AJ31 -> 0 | AL31: =AM31+AN31 -> 0 | AP31: =AQ31+AR31 -> 0 | AT31: =AU31+AV31 -> 0 | AX31: =B31+F31+J31+N31+R31+V31+Z31+AD31+AH31+AL31+AP31+AT31 -> 0 | AY31: =C31+G31+K31+O31+S31+W31+AA31+AE31+AI31+AM31+AQ31+AU31 -> 0 | AZ31: =D31+H31+L31+P31+T31+X31+AB31+AF31+AJ31+AN31+AR31+AV31 -> 0
A32: Assinatura Digital/aplicativo | B32: =C32+D32 -> 0 | F32: =G32+H32 -> 0 | J32: =K32+L32 -> 0 | N32: =O32+P32 -> 0 | R32: =S32+T32 -> 0 | V32: =W32+X32 -> 0 | Z32: =AA32+AB32 -> 0 | AD32: =AE32+AF32 -> 0 | AH32: =AI32+AJ32 -> 0 | AL32: =AM32+AN32 -> 0 | AP32: =AQ32+AR32 -> 0 | AT32: =AU32+AV32 -> 0 | AX32: =B32+F32+J32+N32+R32+V32+Z32+AD32+AH32+AL32+AP32+AT32 -> 0 | AY32: =C32+G32+K32+O32+S32+W32+AA32+AE32+AI32+AM32+AQ32+AU32 -> 0 | AZ32: =D32+H32+L32+P32+T32+X32+AB32+AF32+AJ32+AN32+AR32+AV32 -> 0
A33: Café para Equipe | B33: =C33+D33 -> 226.92 | C33: =127.39+99.53 -> 226.92 | F33: =G33+H33 -> 437.46 | G33: =379.53+57.93 -> 437.46 | J33: =K33+L33 -> 0 | N33: =O33+P33 -> 0 | R33: =S33+T33 -> 0 | V33: =W33+X33 -> 0 | Z33: =AA33+AB33 -> 0 | AD33: =AE33+AF33 -> 0 | AH33: =AI33+AJ33 -> 0 | AL33: =AM33+AN33 -> 0 | AP33: =AQ33+AR33 -> 0 | AT33: =AU33+AV33 -> 0 | AX33: =B33+F33+J33+N33+R33+V33+Z33+AD33+AH33+AL33+AP33+AT33 -> 664.38 | AY33: =C33+G33+K33+O33+S33+W33+AA33+AE33+AI33+AM33+AQ33+AU33 -> 664.38 | AZ33: =D33+H33+L33+P33+T33+X33+AB33+AF33+AJ33+AN33+AR33+AV33 -> 0
A34: Campanha Agenciamento (voulcher p almço) | B34: =C34+D34 -> 0 | F34: =G34+H34 -> 0 | J34: =K34+L34 -> 0 | N34: =O34+P34 -> 0 | R34: =S34+T34 -> 0 | V34: =W34+X34 -> 0 | Z34: =AA34+AB34 -> 0 | AD34: =AE34+AF34 -> 0 | AH34: =AI34+AJ34 -> 0 | AL34: =AM34+AN34 -> 0 | AP34: =AQ34+AR34 -> 0 | AT34: =AU34+AV34 -> 0 | AX34: =B34+F34+J34+N34+R34+V34+Z34+AD34+AH34+AL34+AP34+AT34 -> 0 | AY34: =C34+G34+K34+O34+S34+W34+AA34+AE34+AI34+AM34+AQ34+AU34 -> 0 | AZ34: =D34+H34+L34+P34+T34+X34+AB34+AF34+AJ34+AN34+AR34+AV34 -> 0
A35: Campanha Semestral | B35: =C35+D35 -> 0 | F35: =G35+H35 -> 0 | J35: =K35+L35 -> 0 | N35: =O35+P35 -> 0 | R35: =S35+T35 -> 0 | V35: =W35+X35 -> 0 | Z35: =AA35+AB35 -> 0 | AD35: =AE35+AF35 -> 0 | AH35: =AI35+AJ35 -> 0 | AL35: =AM35+AN35 -> 0 | AP35: =AQ35+AR35 -> 0 | AT35: =AU35+AV35 -> 0 | AX35: =B35+F35+J35+N35+R35+V35+Z35+AD35+AH35+AL35+AP35+AT35 -> 0 | AY35: =C35+G35+K35+O35+S35+W35+AA35+AE35+AI35+AM35+AQ35+AU35 -> 0 | AZ35: =D35+H35+L35+P35+T35+X35+AB35+AF35+AJ35+AN35+AR35+AV35 -> 0
A36: Campanhas outras | B36: =C36+D36 -> 0 | F36: =G36+H36 -> 0 | J36: =K36+L36 -> 0 | N36: =O36+P36 -> 0 | R36: =S36+T36 -> 0 | V36: =W36+X36 -> 0 | Z36: =AA36+AB36 -> 0 | AD36: =AE36+AF36 -> 0 | AH36: =AI36+AJ36 -> 0 | AL36: =AM36+AN36 -> 0 | AP36: =AQ36+AR36 -> 0 | AT36: =AU36+AV36 -> 0 | AX36: =B36+F36+J36+N36+R36+V36+Z36+AD36+AH36+AL36+AP36+AT36 -> 0 | AY36: =C36+G36+K36+O36+S36+W36+AA36+AE36+AI36+AM36+AQ36+AU36 -> 0 | AZ36: =D36+H36+L36+P36+T36+X36+AB36+AF36+AJ36+AN36+AR36+AV36 -> 0
A37: Cartões de visita | B37: =C37+D37 -> 0 | F37: =G37+H37 -> 0 | J37: =K37+L37 -> 0 | N37: =O37+P37 -> 0 | R37: =S37+T37 -> 0 | V37: =W37+X37 -> 0 | Z37: =AA37+AB37 -> 0 | AD37: =AE37+AF37 -> 0 | AH37: =AI37+AJ37 -> 0 | AL37: =AM37+AN37 -> 0 | AP37: =AQ37+AR37 -> 0 | AT37: =AU37+AV37 -> 0 | AX37: =B37+F37+J37+N37+R37+V37+Z37+AD37+AH37+AL37+AP37+AT37 -> 0 | AY37: =C37+G37+K37+O37+S37+W37+AA37+AE37+AI37+AM37+AQ37+AU37 -> 0 | AZ37: =D37+H37+L37+P37+T37+X37+AB37+AF37+AJ37+AN37+AR37+AV37 -> 0
A38: Certidões/procuração/matrículas | B38: =C38+D38 -> 0 | F38: =G38+H38 -> 0 | J38: =K38+L38 -> 0 | N38: =O38+P38 -> 0 | R38: =S38+T38 -> 0 | V38: =W38+X38 -> 0 | Z38: =AA38+AB38 -> 0 | AD38: =AE38+AF38 -> 0 | AH38: =AI38+AJ38 -> 0 | AI38: =-26.45+26.45 -> 0 | AL38: =AM38+AN38 -> 0 | AP38: =AQ38+AR38 -> 0 | AT38: =AU38+AV38 -> 0 | AX38: =B38+F38+J38+N38+R38+V38+Z38+AD38+AH38+AL38+AP38+AT38 -> 0 | AY38: =C38+G38+K38+O38+S38+W38+AA38+AE38+AI38+AM38+AQ38+AU38 -> 0 | AZ38: =D38+H38+L38+P38+T38+X38+AB38+AF38+AJ38+AN38+AR38+AV38 -> 0
A39: CHAVE NA MÃO | B39: =C39+D39 -> 0 | F39: =G39+H39 -> 0 | J39: =K39+L39 -> 0 | N39: =O39+P39 -> 0 | R39: =S39+T39 -> 0 | V39: =W39+X39 -> 0 | Z39: =AA39+AB39 -> 0 | AD39: =AE39+AF39 -> 0 | AH39: =AI39+AJ39 -> 0 | AL39: =AM39+AN39 -> 0 | AP39: =AQ39+AR39 -> 0 | AT39: =AU39+AV39 -> 0 | AX39: =B39+F39+J39+N39+R39+V39+Z39+AD39+AH39+AL39+AP39+AT39 -> 0 | AY39: =C39+G39+K39+O39+S39+W39+AA39+AE39+AI39+AM39+AQ39+AU39 -> 0 | AZ39: =D39+H39+L39+P39+T39+X39+AB39+AF39+AJ39+AN39+AR39+AV39 -> 0
A40: Chaveiros (identicação de chaves) | B40: =C40+D40 -> 0 | F40: =G40+H40 -> 0 | J40: =K40+L40 -> 0 | N40: =O40+P40 -> 0 | R40: =S40+T40 -> 0 | V40: =W40+X40 -> 0 | Z40: =AA40+AB40 -> 0 | AD40: =AE40+AF40 -> 0 | AH40: =AI40+AJ40 -> 0 | AL40: =AM40+AN40 -> 0 | AP40: =AQ40+AR40 -> 0 | AT40: =AU40+AV40 -> 0 | AX40: =B40+F40+J40+N40+R40+V40+Z40+AD40+AH40+AL40+AP40+AT40 -> 0 | AY40: =C40+G40+K40+O40+S40+W40+AA40+AE40+AI40+AM40+AQ40+AU40 -> 0 | AZ40: =D40+H40+L40+P40+T40+X40+AB40+AF40+AJ40+AN40+AR40+AV40 -> 0
A41: CHECKON | B41: =C41+D41 -> 0 | F41: =G41+H41 -> 197.76 | G41: =I41*$BA41/100 -> 197.76 | H41: =I41*$BB41/100 -> 0 | I41: =99.5+98.26 -> 197.76 | J41: =K41+L41 -> 0 | K41: =M41*$BA41/100 -> 0 | L41: =M41*$BB41/100 -> 0 | N41: =O41+P41 -> 0 | O41: =Q41*$BA41/100 -> 0 | P41: =Q41*$BB41/100 -> 0 | R41: =S41+T41 -> 0 | S41: =U41*$BA41/100 -> 0 | T41: =U41*$BB41/100 -> 0 | V41: =W41+X41 -> 0 | W41: =Y41*$BA41/100 -> 0 | X41: =Y41*$BB41/100 -> 0 | Z41: =AA41+AB41 -> 0 | AA41: =AC41*$BA41/100 -> 0 | AB41: =AC41*$BB41/100 -> 0 | AD41: =AE41+AF41 -> 0 | AE41: =AG41*$BA41/100 -> 0 | AF41: =AG41*$BB41/100 -> 0 | AH41: =AI41+AJ41 -> 0 | AI41: =AK41*$BA41/100 -> 0 | AJ41: =AK41*$BB41/100 -> 0 | AL41: =AM41+AN41 -> 0 | AM41: =AO41*$BA41/100 -> 0 | AN41: =AO41*$BB41/100 -> 0 | AP41: =AQ41+AR41 -> 0 | AQ41: =AS41*$BA41/100 -> 0 | AR41: =AS41*$BB41/100 -> 0 | AT41: =AU41+AV41 -> 0 | AU41: =AW41*$BA41/100 -> 0 | AV41: =AW41*$BB41/100 -> 0 | AX41: =B41+F41+J41+N41+R41+V41+Z41+AD41+AH41+AL41+AP41+AT41 -> 197.76 | AY41: =C41+G41+K41+O41+S41+W41+AA41+AE41+AI41+AM41+AQ41+AU41 -> 197.76 | AZ41: =D41+H41+L41+P41+T41+X41+AB41+AF41+AJ41+AN41+AR41+AV41 -> 0 | BA41: =BC$1 -> 100 | BB41: =100-BA41 -> 0 | BC41: =AX41*(BB41/100) -> 0
A42: Creci PF | B42: =C42+D42 -> 0 | F42: =G42+H42 -> 0 | J42: =K42+L42 -> 0 | N42: =O42+P42 -> 0 | R42: =S42+T42 -> 0 | V42: =W42+X42 -> 0 | Z42: =AA42+AB42 -> 0 | AD42: =AE42+AF42 -> 0 | AH42: =AI42+AJ42 -> 0 | AL42: =AM42+AN42 -> 0 | AP42: =AQ42+AR42 -> 0 | AT42: =AU42+AV42 -> 0 | AX42: =B42+F42+J42+N42+R42+V42+Z42+AD42+AH42+AL42+AP42+AT42 -> 0 | AY42: =C42+G42+K42+O42+S42+W42+AA42+AE42+AI42+AM42+AQ42+AU42 -> 0 | AZ42: =D42+H42+L42+P42+T42+X42+AB42+AF42+AJ42+AN42+AR42+AV42 -> 0
A43: Creci PJ | B43: =C43+D43 -> 0 | F43: =G43+H43 -> 0 | J43: =K43+L43 -> 0 | N43: =O43+P43 -> 0 | R43: =S43+T43 -> 0 | V43: =W43+X43 -> 0 | Z43: =AA43+AB43 -> 0 | AD43: =AE43+AF43 -> 0 | AH43: =AI43+AJ43 -> 0 | AL43: =AM43+AN43 -> 0 | AP43: =AQ43+AR43 -> 0 | AT43: =AU43+AV43 -> 0 | AX43: =B43+F43+J43+N43+R43+V43+Z43+AD43+AH43+AL43+AP43+AT43 -> 0 | AY43: =C43+G43+K43+O43+S43+W43+AA43+AE43+AI43+AM43+AQ43+AU43 -> 0 | AZ43: =D43+H43+L43+P43+T43+X43+AB43+AF43+AJ43+AN43+AR43+AV43 -> 0
A44: Cópia de chaves | B44: =C44+D44 -> 140 | D44: 140 | F44: =G44+H44 -> 45 | H44: =15+30 -> 45 | J44: =K44+L44 -> 0 | N44: =O44+P44 -> 0 | R44: =S44+T44 -> 0 | V44: =W44+X44 -> 0 | Z44: =AA44+AB44 -> 0 | AD44: =AE44+AF44 -> 0 | AH44: =AI44+AJ44 -> 0 | AL44: =AM44+AN44 -> 0 | AP44: =AQ44+AR44 -> 0 | AT44: =AU44+AV44 -> 0 | AX44: =B44+F44+J44+N44+R44+V44+Z44+AD44+AH44+AL44+AP44+AT44 -> 185 | AY44: =C44+G44+K44+O44+S44+W44+AA44+AE44+AI44+AM44+AQ44+AU44 -> 0 | AZ44: =D44+H44+L44+P44+T44+X44+AB44+AF44+AJ44+AN44+AR44+AV44 -> 185
A45: Disparos | B45: =C45+D45 -> 0 | F45: =G45+H45 -> 0 | J45: =K45+L45 -> 0 | N45: =O45+P45 -> 0 | R45: =S45+T45 -> 0 | V45: =W45+X45 -> 0 | Z45: =AA45+AB45 -> 0 | AD45: =AE45+AF45 -> 0 | AH45: =AI45+AJ45 -> 0 | AL45: =AM45+AN45 -> 0 | AP45: =AQ45+AR45 -> 0 | AT45: =AU45+AV45 -> 0 | AX45: =B45+F45+J45+N45+R45+V45+Z45+AD45+AH45+AL45+AP45+AT45 -> 0 | AY45: =C45+G45+K45+O45+S45+W45+AA45+AE45+AI45+AM45+AQ45+AU45 -> 0 | AZ45: =D45+H45+L45+P45+T45+X45+AB45+AF45+AJ45+AN45+AR45+AV45 -> 0
A46: Espumante | B46: =C46+D46 -> 0 | F46: =G46+H46 -> 0 | J46: =K46+L46 -> 0 | N46: =O46+P46 -> 0 | R46: =S46+T46 -> 0 | V46: =W46+X46 -> 0 | Z46: =AA46+AB46 -> 0 | AD46: =AE46+AF46 -> 0 | AH46: =AI46+AJ46 -> 0 | AL46: =AM46+AN46 -> 0 | AP46: =AQ46+AR46 -> 0 | AT46: =AU46+AV46 -> 0 | AX46: =B46+F46+J46+N46+R46+V46+Z46+AD46+AH46+AL46+AP46+AT46 -> 0 | AY46: =C46+G46+K46+O46+S46+W46+AA46+AE46+AI46+AM46+AQ46+AU46 -> 0 | AZ46: =D46+H46+L46+P46+T46+X46+AB46+AF46+AJ46+AN46+AR46+AV46 -> 0
A47: Etiquetas | B47: =C47+D47 -> 0 | F47: =G47+H47 -> 0 | J47: =K47+L47 -> 0 | N47: =O47+P47 -> 0 | R47: =S47+T47 -> 0 | V47: =W47+X47 -> 0 | Z47: =AA47+AB47 -> 0 | AD47: =AE47+AF47 -> 0 | AH47: =AI47+AJ47 -> 0 | AL47: =AM47+AN47 -> 0 | AP47: =AQ47+AR47 -> 0 | AT47: =AU47+AV47 -> 0 | AX47: =B47+F47+J47+N47+R47+V47+Z47+AD47+AH47+AL47+AP47+AT47 -> 0 | AY47: =C47+G47+K47+O47+S47+W47+AA47+AE47+AI47+AM47+AQ47+AU47 -> 0 | AZ47: =D47+H47+L47+P47+T47+X47+AB47+AF47+AJ47+AN47+AR47+AV47 -> 0
A48: EVENTOS | B48: =C48+D48 -> 0 | F48: =G48+H48 -> 0 | J48: =K48+L48 -> 260 | K48: 260 | N48: =O48+P48 -> 0 | R48: =S48+T48 -> 0 | V48: =W48+X48 -> 0 | Z48: =AA48+AB48 -> 0 | AD48: =AE48+AF48 -> 0 | AH48: =AI48+AJ48 -> 0 | AL48: =AM48+AN48 -> 0 | AP48: =AQ48+AR48 -> 0 | AT48: =AU48+AV48 -> 0 | AX48: =B48+F48+J48+N48+R48+V48+Z48+AD48+AH48+AL48+AP48+AT48 -> 260 | AY48: =C48+G48+K48+O48+S48+W48+AA48+AE48+AI48+AM48+AQ48+AU48 -> 260 | AZ48: =D48+H48+L48+P48+T48+X48+AB48+AF48+AJ48+AN48+AR48+AV48 -> 0
A49: Facebook/instagran - impulsionamento | B49: =C49+D49 -> 0 | F49: =G49+H49 -> 0 | J49: =K49+L49 -> 0 | N49: =O49+P49 -> 0 | R49: =S49+T49 -> 0 | V49: =W49+X49 -> 0 | Z49: =AA49+AB49 -> 0 | AD49: =AE49+AF49 -> 0 | AH49: =AI49+AJ49 -> 0 | AL49: =AM49+AN49 -> 0 | AP49: =AQ49+AR49 -> 0 | AT49: =AU49+AV49 -> 0 | AX49: =B49+F49+J49+N49+R49+V49+Z49+AD49+AH49+AL49+AP49+AT49 -> 0 | AY49: =C49+G49+K49+O49+S49+W49+AA49+AE49+AI49+AM49+AQ49+AU49 -> 0 | AZ49: =D49+H49+L49+P49+T49+X49+AB49+AF49+AJ49+AN49+AR49+AV49 -> 0
A50: Facebook/instagran - mensal | B50: =C50+D50 -> 0 | F50: =G50+H50 -> 0 | J50: =K50+L50 -> 0 | N50: =O50+P50 -> 0 | R50: =S50+T50 -> 0 | V50: =W50+X50 -> 0 | Z50: =AA50+AB50 -> 0 | AD50: =AE50+AF50 -> 0 | AH50: =AI50+AJ50 -> 0 | AL50: =AM50+AN50 -> 0 | AP50: =AQ50+AR50 -> 0 | AT50: =AU50+AV50 -> 0 | AX50: =B50+F50+J50+N50+R50+V50+Z50+AD50+AH50+AL50+AP50+AT50 -> 0 | AY50: =C50+G50+K50+O50+S50+W50+AA50+AE50+AI50+AM50+AQ50+AU50 -> 0 | AZ50: =D50+H50+L50+P50+T50+X50+AB50+AF50+AJ50+AN50+AR50+AV50 -> 0
A51: Faixas/ Baners | B51: =C51+D51 -> 0 | F51: =G51+H51 -> 0 | J51: =K51+L51 -> 0 | N51: =O51+P51 -> 0 | R51: =S51+T51 -> 0 | V51: =W51+X51 -> 0 | Z51: =AA51+AB51 -> 0 | AD51: =AE51+AF51 -> 0 | AH51: =AI51+AJ51 -> 0 | AL51: =AM51+AN51 -> 0 | AP51: =AQ51+AR51 -> 0 | AT51: =AU51+AV51 -> 0 | AX51: =B51+F51+J51+N51+R51+V51+Z51+AD51+AH51+AL51+AP51+AT51 -> 0 | AY51: =C51+G51+K51+O51+S51+W51+AA51+AE51+AI51+AM51+AQ51+AU51 -> 0 | AZ51: =D51+H51+L51+P51+T51+X51+AB51+AF51+AJ51+AN51+AR51+AV51 -> 0
A52: Folders / Panfletos em geral | B52: =C52+D52 -> 0 | F52: =G52+H52 -> 0 | J52: =K52+L52 -> 0 | N52: =O52+P52 -> 0 | R52: =S52+T52 -> 0 | V52: =W52+X52 -> 0 | Z52: =AA52+AB52 -> 0 | AD52: =AE52+AF52 -> 0 | AH52: =AI52+AJ52 -> 0 | AL52: =AM52+AN52 -> 0 | AP52: =AQ52+AR52 -> 0 | AT52: =AU52+AV52 -> 0 | AX52: =B52+F52+J52+N52+R52+V52+Z52+AD52+AH52+AL52+AP52+AT52 -> 0 | AY52: =C52+G52+K52+O52+S52+W52+AA52+AE52+AI52+AM52+AQ52+AU52 -> 0 | AZ52: =D52+H52+L52+P52+T52+X52+AB52+AF52+AJ52+AN52+AR52+AV52 -> 0
A53: Folha timbrada | B53: =C53+D53 -> 0 | F53: =G53+H53 -> 0 | J53: =K53+L53 -> 0 | N53: =O53+P53 -> 0 | R53: =S53+T53 -> 0 | V53: =W53+X53 -> 0 | Z53: =AA53+AB53 -> 0 | AD53: =AE53+AF53 -> 0 | AH53: =AI53+AJ53 -> 0 | AL53: =AM53+AN53 -> 0 | AP53: =AQ53+AR53 -> 0 | AT53: =AU53+AV53 -> 0 | AX53: =B53+F53+J53+N53+R53+V53+Z53+AD53+AH53+AL53+AP53+AT53 -> 0 | AY53: =C53+G53+K53+O53+S53+W53+AA53+AE53+AI53+AM53+AQ53+AU53 -> 0 | AZ53: =D53+H53+L53+P53+T53+X53+AB53+AF53+AJ53+AN53+AR53+AV53 -> 0
A54: Folha timbrada vitrine | B54: =C54+D54 -> 0 | F54: =G54+H54 -> 0 | J54: =K54+L54 -> 0 | N54: =O54+P54 -> 0 | R54: =S54+T54 -> 0 | V54: =W54+X54 -> 0 | Z54: =AA54+AB54 -> 0 | AD54: =AE54+AF54 -> 0 | AH54: =AI54+AJ54 -> 0 | AL54: =AM54+AN54 -> 0 | AP54: =AQ54+AR54 -> 0 | AT54: =AU54+AV54 -> 0 | AX54: =B54+F54+J54+N54+R54+V54+Z54+AD54+AH54+AL54+AP54+AT54 -> 0 | AY54: =C54+G54+K54+O54+S54+W54+AA54+AE54+AI54+AM54+AQ54+AU54 -> 0 | AZ54: =D54+H54+L54+P54+T54+X54+AB54+AF54+AJ54+AN54+AR54+AV54 -> 0
A55: FOTOS | B55: =C55+D55 -> 2250 | C55: =2250/2 -> 1125 | D55: =2250/2 -> 1125 | F55: =G55+H55 -> 2250 | G55: =I55/2 -> 1125 | H55: =I55/2 -> 1125 | I55: 2250 | J55: =K55+L55 -> 2250 | K55: =2250/2 -> 1125 | L55: =2250/2 -> 1125 | N55: =O55+P55 -> 0 | R55: =S55+T55 -> 0 | V55: =W55+X55 -> 0 | Z55: =AA55+AB55 -> 0 | AD55: =AE55+AF55 -> 0 | AH55: =AI55+AJ55 -> 0 | AL55: =AM55+AN55 -> 0 | AP55: =AQ55+AR55 -> 0 | AT55: =AU55+AV55 -> 0 | AX55: =B55+F55+J55+N55+R55+V55+Z55+AD55+AH55+AL55+AP55+AT55 -> 6750 | AY55: =C55+G55+K55+O55+S55+W55+AA55+AE55+AI55+AM55+AQ55+AU55 -> 3375 | AZ55: =D55+H55+L55+P55+T55+X55+AB55+AF55+AJ55+AN55+AR55+AV55 -> 3375
A56: VIDEO | B56: =C56+D56 -> 0 | F56: =G56+H56 -> 0 | J56: =K56+L56 -> 0 | N56: =O56+P56 -> 0 | R56: =S56+T56 -> 0 | V56: =W56+X56 -> 0 | Z56: =AA56+AB56 -> 0 | AD56: =AE56+AF56 -> 0 | AH56: =AI56+AJ56 -> 0 | AL56: =AM56+AN56 -> 0 | AP56: =AQ56+AR56 -> 0 | AT56: =AU56+AV56 -> 0 | AX56: =B56+F56+J56+N56+R56+V56+Z56+AD56+AH56+AL56+AP56+AT56 -> 0 | AY56: =C56+G56+K56+O56+S56+W56+AA56+AE56+AI56+AM56+AQ56+AU56 -> 0 | AZ56: =D56+H56+L56+P56+T56+X56+AB56+AF56+AJ56+AN56+AR56+AV56 -> 0
A57: GOOGLE IMPULSIONAMENTO | B57: =C57+D57 -> 0 | F57: =G57+H57 -> 500 | G57: =250+250 -> 500 | J57: =K57+L57 -> 500 | K57: 500 | N57: =O57+P57 -> 0 | R57: =S57+T57 -> 0 | V57: =W57+X57 -> 0 | Z57: =AA57+AB57 -> 0 | AD57: =AE57+AF57 -> 0 | AH57: =AI57+AJ57 -> 0 | AL57: =AM57+AN57 -> 0 | AP57: =AQ57+AR57 -> 0 | AT57: =AU57+AV57 -> 0 | AX57: =B57+F57+J57+N57+R57+V57+Z57+AD57+AH57+AL57+AP57+AT57 -> 1000 | AY57: =C57+G57+K57+O57+S57+W57+AA57+AE57+AI57+AM57+AQ57+AU57 -> 1000 | AZ57: =D57+H57+L57+P57+T57+X57+AB57+AF57+AJ57+AN57+AR57+AV57 -> 0
A58: GOOGLE MENSAL | B58: =C58+D58 -> 0 | F58: =G58+H58 -> 0 | J58: =K58+L58 -> 0 | N58: =O58+P58 -> 0 | R58: =S58+T58 -> 0 | V58: =W58+X58 -> 0 | Z58: =AA58+AB58 -> 0 | AD58: =AE58+AF58 -> 0 | AH58: =AI58+AJ58 -> 0 | AL58: =AM58+AN58 -> 0 | AP58: =AQ58+AR58 -> 0 | AT58: =AU58+AV58 -> 0 | AX58: =B58+F58+J58+N58+R58+V58+Z58+AD58+AH58+AL58+AP58+AT58 -> 0 | AY58: =C58+G58+K58+O58+S58+W58+AA58+AE58+AI58+AM58+AQ58+AU58 -> 0 | AZ58: =D58+H58+L58+P58+T58+X58+AB58+AF58+AJ58+AN58+AR58+AV58 -> 0
A59: IA VENDA - LUAN | B59: =C59+D59 -> 0 | F59: =G59+H59 -> 0 | J59: =K59+L59 -> 0 | N59: =O59+P59 -> 0 | R59: =S59+T59 -> 0 | V59: =W59+X59 -> 0 | Z59: =AA59+AB59 -> 0 | AD59: =AE59+AF59 -> 0 | AH59: =AI59+AJ59 -> 0 | AL59: =AM59+AN59 -> 0 | AP59: =AQ59+AR59 -> 0 | AT59: =AU59+AV59 -> 0 | AX59: =B59+F59+J59+N59+R59+V59+Z59+AD59+AH59+AL59+AP59+AT59 -> 0 | AY59: =C59+G59+K59+O59+S59+W59+AA59+AE59+AI59+AM59+AQ59+AU59 -> 0 | AZ59: =D59+H59+L59+P59+T59+X59+AB59+AF59+AJ59+AN59+AR59+AV59 -> 0
A60: IA ALUGUEL - LUAN | B60: =C60+D60 -> 1370 | D60: 1370 | F60: =G60+H60 -> 0 | J60: =K60+L60 -> 2605 | L60: =1370+1235 -> 2605 | N60: =O60+P60 -> 0 | R60: =S60+T60 -> 0 | V60: =W60+X60 -> 0 | Z60: =AA60+AB60 -> 0 | AD60: =AE60+AF60 -> 0 | AH60: =AI60+AJ60 -> 0 | AL60: =AM60+AN60 -> 0 | AP60: =AQ60+AR60 -> 0 | AT60: =AU60+AV60 -> 0 | AX60: =B60+F60+J60+N60+R60+V60+Z60+AD60+AH60+AL60+AP60+AT60 -> 3975 | AY60: =C60+G60+K60+O60+S60+W60+AA60+AE60+AI60+AM60+AQ60+AU60 -> 0 | AZ60: =D60+H60+L60+P60+T60+X60+AB60+AF60+AJ60+AN60+AR60+AV60 -> 3975
A61: Douglas Redes Sociais e Site | B61: =C61+D61 -> 2000 | C61: 2000 | F61: =G61+H61 -> 0 | J61: =K61+L61 -> 2000 | K61: 2000 | N61: =O61+P61 -> 0 | R61: =S61+T61 -> 0 | V61: =W61+X61 -> 0 | Z61: =AA61+AB61 -> 0 | AD61: =AE61+AF61 -> 0 | AH61: =AI61+AJ61 -> 0 | AI61: 0 | AL61: =AM61+AN61 -> 0 | AP61: =AQ61+AR61 -> 0 | AT61: =AU61+AV61 -> 0 | AX61: =B61+F61+J61+N61+R61+V61+Z61+AD61+AH61+AL61+AP61+AT61 -> 4000 | AY61: =C61+G61+K61+O61+S61+W61+AA61+AE61+AI61+AM61+AQ61+AU61 -> 4000 | AZ61: =D61+H61+L61+P61+T61+X61+AB61+AF61+AJ61+AN61+AR61+AV61 -> 0
A62: Indicas e Agenciamentos | B62: =C62+D62 -> 0 | F62: =G62+H62 -> 100 | H62: =50+50 -> 100 | J62: =K62+L62 -> 0 | N62: =O62+P62 -> 0 | R62: =S62+T62 -> 0 | V62: =W62+X62 -> 0 | Z62: =AA62+AB62 -> 0 | AD62: =AE62+AF62 -> 0 | AH62: =AI62+AJ62 -> 0 | AL62: =AM62+AN62 -> 0 | AP62: =AQ62+AR62 -> 0 | AT62: =AU62+AV62 -> 0 | AX62: =B62+F62+J62+N62+R62+V62+Z62+AD62+AH62+AL62+AP62+AT62 -> 100 | AY62: =C62+G62+K62+O62+S62+W62+AA62+AE62+AI62+AM62+AQ62+AU62 -> 0 | AZ62: =D62+H62+L62+P62+T62+X62+AB62+AF62+AJ62+AN62+AR62+AV62 -> 100
A63: INFOQUALY | B63: =C63+D63 -> 136.95 | C63: =E63*$BA63/100 -> 136.95 | D63: =E63*$BB63/100 -> 0 | E63: 136.95 | F63: =G63+H63 -> 136.39 | G63: =I63*$BA63/100 -> 136.39 | H63: =I63*$BB63/100 -> 0 | I63: 136.39 | J63: =K63+L63 -> 0 | K63: =M63*$BA63/100 -> 0 | L63: =M63*$BB63/100 -> 0 | N63: =O63+P63 -> 0 | O63: =Q63*$BA63/100 -> 0 | P63: =Q63*$BB63/100 -> 0 | R63: =S63+T63 -> 0 | S63: =U63*$BA63/100 -> 0 | T63: =U63*$BB63/100 -> 0 | V63: =W63+X63 -> 0 | W63: =Y63*$BA63/100 -> 0 | X63: =Y63*$BB63/100 -> 0 | Z63: =AA63+AB63 -> 0 | AA63: =AC63*$BA63/100 -> 0 | AB63: =AC63*$BB63/100 -> 0 | AD63: =AE63+AF63 -> 0 | AE63: =AG63*$BA63/100 -> 0 | AF63: =AG63*$BB63/100 -> 0 | AH63: =AI63+AJ63 -> 0 | AI63: =AK63*$BA63/100 -> 0 | AJ63: =AK63*$BB63/100 -> 0 | AL63: =AM63+AN63 -> 0 | AM63: =AO63*$BA63/100 -> 0 | AN63: =AO63*$BB63/100 -> 0 | AP63: =AQ63+AR63 -> 0 | AQ63: =AS63*$BA63/100 -> 0 | AR63: =AS63*$BB63/100 -> 0 | AT63: =AU63+AV63 -> 0 | AU63: =AW63*$BA63/100 -> 0 | AV63: =AW63*$BB63/100 -> 0 | AX63: =B63+F63+J63+N63+R63+V63+Z63+AD63+AH63+AL63+AP63+AT63 -> 273.34 | AY63: =C63+G63+K63+O63+S63+W63+AA63+AE63+AI63+AM63+AQ63+AU63 -> 273.34 | AZ63: =D63+H63+L63+P63+T63+X63+AB63+AF63+AJ63+AN63+AR63+AV63 -> 0 | BA63: =BC$1 -> 100 | BB63: =100-BA63 -> 0 | BC63: =AX63*(BB63/100) -> 0
A64: Lacre para placas | B64: =C64+D64 -> 0 | F64: =G64+H64 -> 0 | J64: =K64+L64 -> 0 | N64: =O64+P64 -> 0 | R64: =S64+T64 -> 0 | V64: =W64+X64 -> 0 | Z64: =AA64+AB64 -> 0 | AD64: =AE64+AF64 -> 0 | AH64: =AI64+AJ64 -> 0 | AL64: =AM64+AN64 -> 0 | AP64: =AQ64+AR64 -> 0 | AT64: =AU64+AV64 -> 0 | AX64: =B64+F64+J64+N64+R64+V64+Z64+AD64+AH64+AL64+AP64+AT64 -> 0 | AY64: =C64+G64+K64+O64+S64+W64+AA64+AE64+AI64+AM64+AQ64+AU64 -> 0 | AZ64: =D64+H64+L64+P64+T64+X64+AB64+AF64+AJ64+AN64+AR64+AV64 -> 0
A65: Motoboy | B65: =C65+D65 -> 0 | F65: =G65+H65 -> 0 | J65: =K65+L65 -> 0 | N65: =O65+P65 -> 0 | R65: =S65+T65 -> 0 | V65: =W65+X65 -> 0 | Z65: =AA65+AB65 -> 0 | AD65: =AE65+AF65 -> 0 | AH65: =AI65+AJ65 -> 0 | AL65: =AM65+AN65 -> 0 | AP65: =AQ65+AR65 -> 0 | AT65: =AU65+AV65 -> 0 | AX65: =B65+F65+J65+N65+R65+V65+Z65+AD65+AH65+AL65+AP65+AT65 -> 0 | AY65: =C65+G65+K65+O65+S65+W65+AA65+AE65+AI65+AM65+AQ65+AU65 -> 0 | AZ65: =D65+H65+L65+P65+T65+X65+AB65+AF65+AJ65+AN65+AR65+AV65 -> 0
A66: Pastas AP | B66: =C66+D66 -> 0 | F66: =G66+H66 -> 0 | J66: =K66+L66 -> 0 | N66: =O66+P66 -> 0 | R66: =S66+T66 -> 0 | V66: =W66+X66 -> 0 | Z66: =AA66+AB66 -> 0 | AD66: =AE66+AF66 -> 0 | AH66: =AI66+AJ66 -> 0 | AL66: =AM66+AN66 -> 0 | AP66: =AQ66+AR66 -> 0 | AT66: =AU66+AV66 -> 0 | AX66: =B66+F66+J66+N66+R66+V66+Z66+AD66+AH66+AL66+AP66+AT66 -> 0 | AY66: =C66+G66+K66+O66+S66+W66+AA66+AE66+AI66+AM66+AQ66+AU66 -> 0 | AZ66: =D66+H66+L66+P66+T66+X66+AB66+AF66+AJ66+AN66+AR66+AV66 -> 0
A67: Placas flexiveis | B67: =C67+D67 -> 0 | F67: =G67+H67 -> 0 | J67: =K67+L67 -> 0 | N67: =O67+P67 -> 0 | R67: =S67+T67 -> 0 | V67: =W67+X67 -> 0 | Z67: =AA67+AB67 -> 0 | AD67: =AE67+AF67 -> 0 | AH67: =AI67+AJ67 -> 0 | AL67: =AM67+AN67 -> 0 | AP67: =AQ67+AR67 -> 0 | AT67: =AU67+AV67 -> 0 | AX67: =B67+F67+J67+N67+R67+V67+Z67+AD67+AH67+AL67+AP67+AT67 -> 0 | AY67: =C67+G67+K67+O67+S67+W67+AA67+AE67+AI67+AM67+AQ67+AU67 -> 0 | AZ67: =D67+H67+L67+P67+T67+X67+AB67+AF67+AJ67+AN67+AR67+AV67 -> 0
A68: Placas grandes com estacas | B68: =C68+D68 -> 0 | F68: =G68+H68 -> 0 | J68: =K68+L68 -> 0 | N68: =O68+P68 -> 0 | R68: =S68+T68 -> 0 | V68: =W68+X68 -> 0 | Z68: =AA68+AB68 -> 0 | AD68: =AE68+AF68 -> 0 | AH68: =AI68+AJ68 -> 0 | AL68: =AM68+AN68 -> 0 | AP68: =AQ68+AR68 -> 0 | AT68: =AU68+AV68 -> 0 | AX68: =B68+F68+J68+N68+R68+V68+Z68+AD68+AH68+AL68+AP68+AT68 -> 0 | AY68: =C68+G68+K68+O68+S68+W68+AA68+AE68+AI68+AM68+AQ68+AU68 -> 0 | AZ68: =D68+H68+L68+P68+T68+X68+AB68+AF68+AJ68+AN68+AR68+AV68 -> 0
A69: Placas PS | B69: =C69+D69 -> 0 | F69: =G69+H69 -> 0 | J69: =K69+L69 -> 0 | N69: =O69+P69 -> 0 | R69: =S69+T69 -> 0 | V69: =W69+X69 -> 0 | Z69: =AA69+AB69 -> 0 | AD69: =AE69+AF69 -> 0 | AH69: =AI69+AJ69 -> 0 | AL69: =AM69+AN69 -> 0 | AP69: =AQ69+AR69 -> 0 | AT69: =AU69+AV69 -> 0 | AX69: =B69+F69+J69+N69+R69+V69+Z69+AD69+AH69+AL69+AP69+AT69 -> 0 | AY69: =C69+G69+K69+O69+S69+W69+AA69+AE69+AI69+AM69+AQ69+AU69 -> 0 | AZ69: =D69+H69+L69+P69+T69+X69+AB69+AF69+AJ69+AN69+AR69+AV69 -> 0
A70: Presentes | B70: =C70+D70 -> 0 | F70: =G70+H70 -> 0 | J70: =K70+L70 -> 0 | N70: =O70+P70 -> 0 | R70: =S70+T70 -> 0 | V70: =W70+X70 -> 0 | Z70: =AA70+AB70 -> 0 | AD70: =AE70+AF70 -> 0 | AH70: =AI70+AJ70 -> 0 | AL70: =AM70+AN70 -> 0 | AP70: =AQ70+AR70 -> 0 | AT70: =AU70+AV70 -> 0 | AX70: =B70+F70+J70+N70+R70+V70+Z70+AD70+AH70+AL70+AP70+AT70 -> 0 | AY70: =C70+G70+K70+O70+S70+W70+AA70+AE70+AI70+AM70+AQ70+AU70 -> 0 | AZ70: =D70+H70+L70+P70+T70+X70+AB70+AF70+AJ70+AN70+AR70+AV70 -> 0
A71: Procob - créditos | B71: =C71+D71 -> 0 | F71: =G71+H71 -> 0 | J71: =K71+L71 -> 0 | N71: =O71+P71 -> 0 | R71: =S71+T71 -> 0 | V71: =W71+X71 -> 0 | Z71: =AA71+AB71 -> 0 | AD71: =AE71+AF71 -> 0 | AH71: =AI71+AJ71 -> 0 | AL71: =AM71+AN71 -> 0 | AP71: =AQ71+AR71 -> 0 | AT71: =AU71+AV71 -> 0 | AX71: =B71+F71+J71+N71+R71+V71+Z71+AD71+AH71+AL71+AP71+AT71 -> 0 | AY71: =C71+G71+K71+O71+S71+W71+AA71+AE71+AI71+AM71+AQ71+AU71 -> 0 | AZ71: =D71+H71+L71+P71+T71+X71+AB71+AF71+AJ71+AN71+AR71+AV71 -> 0
A72: Procob - mensal | B72: =C72+D72 -> 0 | F72: =G72+H72 -> 0 | J72: =K72+L72 -> 0 | N72: =O72+P72 -> 0 | R72: =S72+T72 -> 0 | V72: =W72+X72 -> 0 | Z72: =AA72+AB72 -> 0 | AD72: =AE72+AF72 -> 0 | AH72: =AI72+AJ72 -> 0 | AL72: =AM72+AN72 -> 0 | AP72: =AQ72+AR72 -> 0 | AT72: =AU72+AV72 -> 0 | AX72: =B72+F72+J72+N72+R72+V72+Z72+AD72+AH72+AL72+AP72+AT72 -> 0 | AY72: =C72+G72+K72+O72+S72+W72+AA72+AE72+AI72+AM72+AQ72+AU72 -> 0 | AZ72: =D72+H72+L72+P72+T72+X72+AB72+AF72+AJ72+AN72+AR72+AV72 -> 0
A73: QR CODE | B73: =C73+D73 -> 0 | F73: =G73+H73 -> 0 | J73: =K73+L73 -> 0 | N73: =O73+P73 -> 0 | R73: =S73+T73 -> 0 | V73: =W73+X73 -> 0 | Z73: =AA73+AB73 -> 0 | AD73: =AE73+AF73 -> 0 | AH73: =AI73+AJ73 -> 0 | AL73: =AM73+AN73 -> 0 | AP73: =AQ73+AR73 -> 0 | AT73: =AU73+AV73 -> 0 | AX73: =B73+F73+J73+N73+R73+V73+Z73+AD73+AH73+AL73+AP73+AT73 -> 0 | AY73: =C73+G73+K73+O73+S73+W73+AA73+AE73+AI73+AM73+AQ73+AU73 -> 0 | AZ73: =D73+H73+L73+P73+T73+X73+AB73+AF73+AJ73+AN73+AR73+AV73 -> 0
A74: QUIRES | B74: =C74+D74 -> 163.89 | C74: 163.89 | F74: =G74+H74 -> 173.96 | G74: 173.96 | J74: =K74+L74 -> 0 | N74: =O74+P74 -> 0 | R74: =S74+T74 -> 0 | V74: =W74+X74 -> 0 | Z74: =AA74+AB74 -> 0 | AD74: =AE74+AF74 -> 0 | AH74: =AI74+AJ74 -> 0 | AL74: =AM74+AN74 -> 0 | AP74: =AQ74+AR74 -> 0 | AT74: =AU74+AV74 -> 0 | AX74: =B74+F74+J74+N74+R74+V74+Z74+AD74+AH74+AL74+AP74+AT74 -> 337.85 | AY74: =C74+G74+K74+O74+S74+W74+AA74+AE74+AI74+AM74+AQ74+AU74 -> 337.85 | AZ74: =D74+H74+L74+P74+T74+X74+AB74+AF74+AJ74+AN74+AR74+AV74 -> 0
A75: SITE | B75: =C75+D75 -> 0 | F75: =G75+H75 -> 0 | J75: =K75+L75 -> 0 | N75: =O75+P75 -> 0 | R75: =S75+T75 -> 0 | V75: =W75+X75 -> 0 | Z75: =AA75+AB75 -> 0 | AD75: =AE75+AF75 -> 0 | AH75: =AI75+AJ75 -> 0 | AL75: =AM75+AN75 -> 0 | AP75: =AQ75+AR75 -> 0 | AT75: =AU75+AV75 -> 0 | AX75: =B75+F75+J75+N75+R75+V75+Z75+AD75+AH75+AL75+AP75+AT75 -> 0 | AY75: =C75+G75+K75+O75+S75+W75+AA75+AE75+AI75+AM75+AQ75+AU75 -> 0 | AZ75: =D75+H75+L75+P75+T75+X75+AB75+AF75+AJ75+AN75+AR75+AV75 -> 0
A76: Uber | B76: =C76+D76 -> 1259.26 | D76: 1259.26 | F76: =G76+H76 -> 1542.71 | H76: 1542.71 | J76: =K76+L76 -> 0 | N76: =O76+P76 -> 0 | R76: =S76+T76 -> 0 | V76: =W76+X76 -> 0 | Z76: =AA76+AB76 -> 0 | AD76: =AE76+AF76 -> 0 | AH76: =AI76+AJ76 -> 0 | AL76: =AM76+AN76 -> 0 | AP76: =AQ76+AR76 -> 0 | AT76: =AU76+AV76 -> 0 | AX76: =B76+F76+J76+N76+R76+V76+Z76+AD76+AH76+AL76+AP76+AT76 -> 2801.97 | AY76: =C76+G76+K76+O76+S76+W76+AA76+AE76+AI76+AM76+AQ76+AU76 -> 0 | AZ76: =D76+H76+L76+P76+T76+X76+AB76+AF76+AJ76+AN76+AR76+AV76 -> 2801.97
A77: Vistorias | B77: =C77+D77 -> 0 | F77: =G77+H77 -> 0 | J77: =K77+L77 -> 0 | N77: =O77+P77 -> 0 | R77: =S77+T77 -> 0 | V77: =W77+X77 -> 0 | Z77: =AA77+AB77 -> 0 | AD77: =AE77+AF77 -> 0 | AH77: =AI77+AJ77 -> 0 | AL77: =AM77+AN77 -> 0 | AP77: =AQ77+AR77 -> 0 | AT77: =AU77+AV77 -> 0 | AX77: =B77+F77+J77+N77+R77+V77+Z77+AD77+AH77+AL77+AP77+AT77 -> 0 | AY77: =C77+G77+K77+O77+S77+W77+AA77+AE77+AI77+AM77+AQ77+AU77 -> 0 | AZ77: =D77+H77+L77+P77+T77+X77+AB77+AF77+AJ77+AN77+AR77+AV77 -> 0
A78: Toner / cartucho | B78: =C78+D78 -> 0 | C78: =E78*$BA78/100 -> 0 | D78: =E78*$BB78/100 -> 0 | F78: =G78+H78 -> 0 | G78: =I78*$BA78/100 -> 0 | H78: =I78*$BB78/100 -> 0 | J78: =K78+L78 -> 0 | K78: =M78*$BA78/100 -> 0 | L78: =M78*$BB78/100 -> 0 | N78: =O78+P78 -> 0 | O78: =Q78*$BA78/100 -> 0 | P78: =Q78*$BB78/100 -> 0 | R78: =S78+T78 -> 0 | S78: =U78*$BA78/100 -> 0 | T78: =U78*$BB78/100 -> 0 | V78: =W78+X78 -> 0 | W78: =Y78*$BA78/100 -> 0 | X78: =Y78*$BB78/100 -> 0 | Z78: =AA78+AB78 -> 0 | AA78: =AC78*$BA78/100 -> 0 | AB78: =AC78*$BB78/100 -> 0 | AD78: =AE78+AF78 -> 0 | AE78: =AG78*$BA78/100 -> 0 | AF78: =AG78*$BB78/100 -> 0 | AH78: =AI78+AJ78 -> 0 | AI78: =AK78*$BA78/100 -> 0 | AJ78: =AK78*$BB78/100 -> 0 | AL78: =AM78+AN78 -> 0 | AM78: =AO78*$BA78/100 -> 0 | AN78: =AO78*$BB78/100 -> 0 | AP78: =AQ78+AR78 -> 0 | AQ78: =AS78*$BA78/100 -> 0 | AR78: =AS78*$BB78/100 -> 0 | AT78: =AU78+AV78 -> 0 | AU78: =AW78*$BA78/100 -> 0 | AV78: =AW78*$BB78/100 -> 0 | AX78: =B78+F78+J78+N78+R78+V78+Z78+AD78+AH78+AL78+AP78+AT78 -> 0 | AY78: =C78+G78+K78+O78+S78+W78+AA78+AE78+AI78+AM78+AQ78+AU78 -> 0 | AZ78: =D78+H78+L78+P78+T78+X78+AB78+AF78+AJ78+AN78+AR78+AV78 -> 0 | BA78: =BC$1 -> 100 | BB78: =100-BA78 -> 0 | BC78: =AX78*(BB78/100) -> 0
A79: ZAP PJ | B79: =C79+D79 -> 5117.87 | C79: 5117.87 | F79: =G79+H79 -> 5117.8 | G79: =1717.8+3400 -> 5117.8 | J79: =K79+L79 -> 0 | N79: =O79+P79 -> 0 | R79: =S79+T79 -> 0 | V79: =W79+X79 -> 0 | Z79: =AA79+AB79 -> 0 | AD79: =AE79+AF79 -> 0 | AH79: =AI79+AJ79 -> 0 | AL79: =AM79+AN79 -> 0 | AP79: =AQ79+AR79 -> 0 | AT79: =AU79+AV79 -> 0 | AX79: =B79+F79+J79+N79+R79+V79+Z79+AD79+AH79+AL79+AP79+AT79 -> 10235.67 | AY79: =C79+G79+K79+O79+S79+W79+AA79+AE79+AI79+AM79+AQ79+AU79 -> 10235.67 | AZ79: =D79+H79+L79+P79+T79+X79+AB79+AF79+AJ79+AN79+AR79+AV79 -> 0
A80: ZAP PF | B80: =C80+D80 -> 0 | F80: =G80+H80 -> 0 | J80: =K80+L80 -> 0 | N80: =O80+P80 -> 0 | R80: =S80+T80 -> 0 | V80: =W80+X80 -> 0 | Z80: =AA80+AB80 -> 0 | AD80: =AE80+AF80 -> 0 | AH80: =AI80+AJ80 -> 0 | AL80: =AM80+AN80 -> 0 | AP80: =AQ80+AR80 -> 0 | AT80: =AU80+AV80 -> 0 | AX80: =B80+F80+J80+N80+R80+V80+Z80+AD80+AH80+AL80+AP80+AT80 -> 0 | AY80: =C80+G80+K80+O80+S80+W80+AA80+AE80+AI80+AM80+AQ80+AU80 -> 0 | AZ80: =D80+H80+L80+P80+T80+X80+AB80+AF80+AJ80+AN80+AR80+AV80 -> 0
A81: Outro | B81: =C81+D81 -> 53.65 | C81: =8+12.5+32.9+0.29-0.04 -> 53.65 | F81: =G81+H81 -> 264.06 | G81: 264.06 | J81: =K81+L81 -> 0 | N81: =O81+P81 -> 0 | R81: =S81+T81 -> 0 | V81: =W81+X81 -> 0 | Z81: =AA81+AB81 -> 0 | AD81: =AE81+AF81 -> 0 | AH81: =AI81+AJ81 -> 0 | AL81: =AM81+AN81 -> 0 | AP81: =AQ81+AR81 -> 0 | AT81: =AU81+AV81 -> 0 | AX81: =B81+F81+J81+N81+R81+V81+Z81+AD81+AH81+AL81+AP81+AT81 -> 317.71 | AY81: =C81+G81+K81+O81+S81+W81+AA81+AE81+AI81+AM81+AQ81+AU81 -> 317.71 | AZ81: =D81+H81+L81+P81+T81+X81+AB81+AF81+AJ81+AN81+AR81+AV81 -> 0
A82: TOTAL GASTOS OPERACIONAIS VENDA | B82: =SUM(B30:B81) -> 12718.54 | C82: =SUM(C30:C81) -> 8824.28 | D82: =SUM(D30:D81) -> 3894.26 | E82: =SUM(E30:E81) -> 136.95 | F82: =SUM(F30:F81) -> 10765.14 | G82: =SUM(G30:G81) -> 7952.43 | H82: =SUM(H30:H81) -> 2812.71 | I82: =SUM(I30:I81) -> 2584.15 | ... AW82: =SUM(AW30:AW81) -> 0 | AX82: =B82+F82+J82+N82+R82+V82+Z82+AD82+AH82+AL82+AP82+AT82 -> 31098.68 | AY82: =C82+G82+K82+O82+S82+W82+AA82+AE82+AI82+AM82+AQ82+AU82 -> 20661.71 | AZ82: =D82+H82+L82+P82+T82+X82+AB82+AF82+AJ82+AN82+AR82+AV82 -> 10436.97 | BC82: =SUM(BC29:BC81) -> 0
A83: DESPESA COM PESSOAS
A84: Folha de Pagamentos | B84: =Folha!C159 -> 17525.89 | C84: =Folha!C155 -> 2110.63 | D84: =Folha!C157 -> 15415.26 | F84: =Folha!D159 -> 4927.06 | G84: =Folha!D155 -> 0 | H84: =Folha!D157 -> 4927.06 | J84: =Folha!E159 -> 22771.15 | K84: =Folha!E155 -> 1721.63 | L84: =Folha!E157 -> 21049.52 | N84: =Folha!F159 -> 0 | O84: =Folha!F155 -> 0 | P84: =Folha!F157 -> 0 | R84: =Folha!G159 -> 0 | S84: =Folha!G155 -> 0 | T84: =Folha!G157 -> 0 | V84: =Folha!H159 -> 0 | W84: =Folha!H155 -> 0 | X84: =Folha!H157 -> 0 | Z84: =Folha!I159 -> 0 | AA84: =Folha!I155 -> 0 | AB84: =Folha!I157 -> 0 | AD84: =Folha!J159 -> 0 | AE84: =Folha!J155 -> 0 | AF84: =Folha!J157 -> 0 | AH84: =Folha!K159 -> 0 | AI84: =Folha!K155 -> 0 | AJ84: =Folha!K157 -> 0 | AL84: =Folha!L159 -> 0 | AM84: =Folha!L155 -> 0 | AN84: =Folha!L157 -> 0 | AP84: =Folha!M159 -> 0 | AQ84: =Folha!M155 -> 0 | AR84: =Folha!M157 -> 0 | AT84: =Folha!N159 -> 0 | AU84: =Folha!N155 -> 0 | AV84: =Folha!N157 -> 0 | AX84: =B84+F84+J84+N84+R84+V84+Z84+AD84+AH84+AL84+AP84+AT84 -> 45224.1 | AY84: =C84+G84+K84+O84+S84+W84+AA84+AE84+AI84+AM84+AQ84+AU84 -> 3832.26 | AZ84: =D84+H84+L84+P84+T84+X84+AB84+AF84+AJ84+AN84+AR84+AV84 -> 41391.84
A85: FGTS | B85: =C85+D85 -> 1662.18 | C85: =E85*$BA85/100 -> 265.9488 | D85: =E85*$BB85/100 -> 1396.2312 | E85: =1091.5+570.68 -> 1662.18 | F85: =G85+H85 -> 622.99 | G85: =I85*$BA85/100 -> 99.6784 | H85: =I85*$BB85/100 -> 523.3116 | I85: 622.99 | J85: =K85+L85 -> 0 | K85: =M85*$BA85/100 -> 0 | L85: =M85*$BB85/100 -> 0 | N85: =O85+P85 -> 0 | O85: =Q85*$BA85/100 -> 0 | P85: =Q85*$BB85/100 -> 0 | R85: =S85+T85 -> 0 | S85: =U85*$BA85/100 -> 0 | T85: =U85*$BB85/100 -> 0 | V85: =W85+X85 -> 0 | W85: =Y85*$BA85/100 -> 0 | X85: =Y85*$BB85/100 -> 0 | Z85: =AA85+AB85 -> 0 | AA85: =AC85*$BA85/100 -> 0 | AB85: =AC85*$BB85/100 -> 0 | AD85: =AE85+AF85 -> 0 | AE85: =AG85*$BA85/100 -> 0 | AF85: =AG85*$BB85/100 -> 0 | AH85: =AI85+AJ85 -> 0 | AI85: =AK85*$BA85/100 -> 0 | AJ85: =AK85*$BB85/100 -> 0 | AL85: =AM85+AN85 -> 0 | AM85: =AO85*$BA85/100 -> 0 | AN85: =AO85*$BB85/100 -> 0 | AP85: =AQ85+AR85 -> 0 | AQ85: =AS85*$BA85/100 -> 0 | AR85: =AS85*$BB85/100 -> 0 | AT85: =AU85+AV85 -> 0 | AU85: =AW85*$BA85/100 -> 0 | AV85: =AW85*$BB85/100 -> 0 | AX85: =B85+F85+J85+N85+R85+V85+Z85+AD85+AH85+AL85+AP85+AT85 -> 2285.17 | AY85: =C85+G85+K85+O85+S85+W85+AA85+AE85+AI85+AM85+AQ85+AU85 -> 365.6272 | AZ85: =D85+H85+L85+P85+T85+X85+AB85+AF85+AJ85+AN85+AR85+AV85 -> 1919.5428 | BA85: 16 | BB85: =100-BA85 -> 84
A86: GPS/INSS | B86: =C86+D86 -> 6399.42 | C86: =E86*$BA86/100 -> 1023.9072 | D86: =E86*$BB86/100 -> 5375.5128 | E86: =1266.22+3752.42+1380.78 -> 6399.42 | F86: =G86+H86 -> 1033.8 | G86: =I86*$BA86/100 -> 165.408 | H86: =I86*$BB86/100 -> 868.392 | I86: 1033.8 | J86: =K86+L86 -> 0 | K86: =M86*$BA86/100 -> 0 | L86: =M86*$BB86/100 -> 0 | N86: =O86+P86 -> 0 | O86: =Q86*$BA86/100 -> 0 | P86: =Q86*$BB86/100 -> 0 | R86: =S86+T86 -> 0 | S86: =U86*$BA86/100 -> 0 | T86: =U86*$BB86/100 -> 0 | V86: =W86+X86 -> 0 | W86: =Y86*$BA86/100 -> 0 | X86: =Y86*$BB86/100 -> 0 | Z86: =AA86+AB86 -> 0 | AA86: =AC86*$BA86/100 -> 0 | AB86: =AC86*$BB86/100 -> 0 | AD86: =AE86+AF86 -> 0 | AE86: =AG86*$BA86/100 -> 0 | AF86: =AG86*$BB86/100 -> 0 | AH86: =AI86+AJ86 -> 0 | AI86: =AK86*$BA86/100 -> 0 | AJ86: =AK86*$BB86/100 -> 0 | AL86: =AM86+AN86 -> 0 | AM86: =AO86*$BA86/100 -> 0 | AN86: =AO86*$BB86/100 -> 0 | AP86: =AQ86+AR86 -> 0 | AQ86: =AS86*$BA86/100 -> 0 | AR86: =AS86*$BB86/100 -> 0 | AT86: =AU86+AV86 -> 0 | AU86: =AW86*$BA86/100 -> 0 | AV86: =AW86*$BB86/100 -> 0 | AX86: =B86+F86+J86+N86+R86+V86+Z86+AD86+AH86+AL86+AP86+AT86 -> 7433.22 | AY86: =C86+G86+K86+O86+S86+W86+AA86+AE86+AI86+AM86+AQ86+AU86 -> 1189.3152 | AZ86: =D86+H86+L86+P86+T86+X86+AB86+AF86+AJ86+AN86+AR86+AV86 -> 6243.9048 | BA86: 16 | BB86: =100-BA86 -> 84
A87: GSO - Esocial | B87: =C87+D87 -> 107.71 | C87: =E87*$BA87/100 -> 17.2336 | D87: =E87*$BB87/100 -> 90.4764 | E87: 107.71 | F87: =G87+H87 -> 0 | G87: =I87*$BA87/100 -> 0 | H87: =I87*$BB87/100 -> 0 | J87: =K87+L87 -> 0 | K87: =M87*$BA87/100 -> 0 | L87: =M87*$BB87/100 -> 0 | N87: =O87+P87 -> 0 | O87: =Q87*$BA87/100 -> 0 | P87: =Q87*$BB87/100 -> 0 | R87: =S87+T87 -> 0 | S87: =U87*$BA87/100 -> 0 | T87: =U87*$BB87/100 -> 0 | V87: =W87+X87 -> 0 | W87: =Y87*$BA87/100 -> 0 | X87: =Y87*$BB87/100 -> 0 | Z87: =AA87+AB87 -> 0 | AA87: =AC87*$BA87/100 -> 0 | AB87: =AC87*$BB87/100 -> 0 | AD87: =AE87+AF87 -> 0 | AE87: =AG87*$BA87/100 -> 0 | AF87: =AG87*$BB87/100 -> 0 | AH87: =AI87+AJ87 -> 0 | AI87: =AK87*$BA87/100 -> 0 | AJ87: =AK87*$BB87/100 -> 0 | AL87: =AM87+AN87 -> 0 | AM87: =AO87*$BA87/100 -> 0 | AN87: =AO87*$BB87/100 -> 0 | AP87: =AQ87+AR87 -> 0 | AQ87: =AS87*$BA87/100 -> 0 | AR87: =AS87*$BB87/100 -> 0 | AT87: =AU87+AV87 -> 0 | AU87: =AW87*$BA87/100 -> 0 | AV87: =AW87*$BB87/100 -> 0 | AX87: =B87+F87+J87+N87+R87+V87+Z87+AD87+AH87+AL87+AP87+AT87 -> 107.71 | AY87: =C87+G87+K87+O87+S87+W87+AA87+AE87+AI87+AM87+AQ87+AU87 -> 17.2336 | AZ87: =D87+H87+L87+P87+T87+X87+AB87+AF87+AJ87+AN87+AR87+AV87 -> 90.4764 | BA87: 16 | BB87: =100-BA87 -> 84
A88: SECOVIMED (Plano de Saúde) | B88: =C88+D88 -> 0 | C88: =E88*$BA88/100 -> 0 | D88: =E88*$BB88/100 -> 0 | F88: =G88+H88 -> 416.48 | G88: =I88*$BA88/100 -> 66.6368 | H88: =I88*$BB88/100 -> 349.8432 | I88: =234.13+182.35 -> 416.48 | J88: =K88+L88 -> 0 | K88: =M88*$BA88/100 -> 0 | L88: =M88*$BB88/100 -> 0 | N88: =O88+P88 -> 0 | O88: =Q88*$BA88/100 -> 0 | P88: =Q88*$BB88/100 -> 0 | R88: =S88+T88 -> 0 | S88: =U88*$BA88/100 -> 0 | T88: =U88*$BB88/100 -> 0 | V88: =W88+X88 -> 0 | W88: =Y88*$BA88/100 -> 0 | X88: =Y88*$BB88/100 -> 0 | Z88: =AA88+AB88 -> 0 | AA88: =AC88*$BA88/100 -> 0 | AB88: =AC88*$BB88/100 -> 0 | AD88: =AE88+AF88 -> 0 | AE88: =AG88*$BA88/100 -> 0 | AF88: =AG88*$BB88/100 -> 0 | AH88: =AI88+AJ88 -> 0 | AI88: =AK88*$BA88/100 -> 0 | AJ88: =AK88*$BB88/100 -> 0 | AL88: =AM88+AN88 -> 0 | AM88: =AO88*$BA88/100 -> 0 | AN88: =AO88*$BB88/100 -> 0 | AP88: =AQ88+AR88 -> 0 | AQ88: =AS88*$BA88/100 -> 0 | AR88: =AS88*$BB88/100 -> 0 | AT88: =AU88+AV88 -> 0 | AU88: =AW88*$BA88/100 -> 0 | AV88: =AW88*$BB88/100 -> 0 | AX88: =B88+F88+J88+N88+R88+V88+Z88+AD88+AH88+AL88+AP88+AT88 -> 416.48 | AY88: =C88+G88+K88+O88+S88+W88+AA88+AE88+AI88+AM88+AQ88+AU88 -> 66.6368 | AZ88: =D88+H88+L88+P88+T88+X88+AB88+AF88+AJ88+AN88+AR88+AV88 -> 349.8432 | BA88: 16 | BB88: =100-BA88 -> 84
A89: TOTAL | B89: =SUM(B84:B88) -> 25695.2 | C89: =SUM(C84:C88) -> 3417.7196 | D89: =SUM(D84:D88) -> 22277.48 | E89: =SUM(E84:E88) -> 8169.31 | F89: =SUM(F84:F88) -> 7000.33 | G89: =SUM(G84:G88) -> 331.7232 | H89: =SUM(H84:H88) -> 6668.6068 | I89: =SUM(I84:I88) -> 2073.27 | ... AW89: =SUM(AW84:AW88) -> 0 | AX89: =B89+F89+J89+N89+R89+V89+Z89+AD89+AH89+AL89+AP89+AT89 -> 55466.68 | AY89: =C89+G89+K89+O89+S89+W89+AA89+AE89+AI89+AM89+AQ89+AU89 -> 5471.0728 | AZ89: =D89+H89+L89+P89+T89+X89+AB89+AF89+AJ89+AN89+AR89+AV89 -> 49995.607 | BC89: =SUM(BC83:BC88) -> 0
A90: CONTAS ADMINISTRATIVAS E FINANCEIRAS
A91: GASTOS ADMINISTRATIVOS | AX91: =B91+F91+J91+N91+R91+V91+Z91+AD91+AH91+AL91+AP91+AT91 -> 0 | AY91: =C91+G91+K91+O91+S91+W91+AA91+AE91+AI91+AM91+AQ91+AU91 -> 0 | AZ91: =D91+H91+L91+P91+T91+X91+AB91+AF91+AJ91+AN91+AR91+AV91 -> 0
A92: Aquisição | B92: =C92+D92 -> 0 | F92: =G92+H92 -> 0 | J92: =K92+L92 -> 0 | N92: =O92+P92 -> 0 | R92: =S92+T92 -> 0 | V92: =W92+X92 -> 0 | Z92: =AA92+AB92 -> 0 | AD92: =AE92+AF92 -> 0 | AH92: =AI92+AJ92 -> 0 | AL92: =AM92+AN92 -> 0 | AP92: =AQ92+AR92 -> 0 | AT92: =AU92+AV92 -> 0 | AX92: =B92+F92+J92+N92+R92+V92+Z92+AD92+AH92+AL92+AP92+AT92 -> 0 | AY92: =C92+G92+K92+O92+S92+W92+AA92+AE92+AI92+AM92+AQ92+AU92 -> 0 | AZ92: =D92+H92+L92+P92+T92+X92+AB92+AF92+AJ92+AN92+AR92+AV92 -> 0
A93: Certificação Digital | B93: =C93+D93 -> 0 | F93: =G93+H93 -> 0 | J93: =K93+L93 -> 0 | N93: =O93+P93 -> 0 | R93: =S93+T93 -> 0 | V93: =W93+X93 -> 0 | Z93: =AA93+AB93 -> 0 | AD93: =AE93+AF93 -> 0 | AH93: =AI93+AJ93 -> 0 | AL93: =AM93+AN93 -> 0 | AP93: =AQ93+AR93 -> 0 | AT93: =AU93+AV93 -> 0 | AX93: =B93+F93+J93+N93+R93+V93+Z93+AD93+AH93+AL93+AP93+AT93 -> 0 | AY93: =C93+G93+K93+O93+S93+W93+AA93+AE93+AI93+AM93+AQ93+AU93 -> 0 | AZ93: =D93+H93+L93+P93+T93+X93+AB93+AF93+AJ93+AN93+AR93+AV93 -> 0
A94: Caixa | B94: =C94+D94 -> 0 | F94: =G94+H94 -> 0 | J94: =K94+L94 -> 0 | N94: =O94+P94 -> 0 | R94: =S94+T94 -> 0 | V94: =W94+X94 -> 0 | Z94: =AA94+AB94 -> 0 | AD94: =AE94+AF94 -> 0 | AH94: =AI94+AJ94 -> 0 | AL94: =AM94+AN94 -> 0 | AP94: =AQ94+AR94 -> 0 | AT94: =AU94+AV94 -> 0 | AX94: =B94+F94+J94+N94+R94+V94+Z94+AD94+AH94+AL94+AP94+AT94 -> 0 | AY94: =C94+G94+K94+O94+S94+W94+AA94+AE94+AI94+AM94+AQ94+AU94 -> 0 | AZ94: =D94+H94+L94+P94+T94+X94+AB94+AF94+AJ94+AN94+AR94+AV94 -> 0
A95: Cartão de crédito BB | B95: =C95+D95 -> 0 | C95: =E95*$BA95/100 -> 0 | D95: =E95*$BB95/100 -> 0 | F95: =G95+H95 -> 0 | G95: =I95*$BA95/100 -> 0 | H95: =I95*$BB95/100 -> 0 | J95: =K95+L95 -> 0 | K95: =M95*$BA95/100 -> 0 | L95: =M95*$BB95/100 -> 0 | N95: =O95+P95 -> 0 | O95: =Q95*$BA95/100 -> 0 | P95: =Q95*$BB95/100 -> 0 | R95: =S95+T95 -> 0 | S95: =U95*$BA95/100 -> 0 | T95: =U95*$BB95/100 -> 0 | V95: =W95+X95 -> 0 | W95: =Y95*$BA95/100 -> 0 | X95: =Y95*$BB95/100 -> 0 | Z95: =AA95+AB95 -> 0 | AA95: =AC95*$BA95/100 -> 0 | AB95: =AC95*$BB95/100 -> 0 | AD95: =AE95+AF95 -> 0 | AE95: =AG95*$BA95/100 -> 0 | AF95: =AG95*$BB95/100 -> 0 | AH95: =AI95+AJ95 -> 0 | AI95: =AK95*$BA95/100 -> 0 | AJ95: =AK95*$BB95/100 -> 0 | AL95: =AM95+AN95 -> 0 | AM95: =AO95*$BA95/100 -> 0 | AN95: =AO95*$BB95/100 -> 0 | AP95: =AQ95+AR95 -> 0 | AQ95: =AS95*$BA95/100 -> 0 | AR95: =AS95*$BB95/100 -> 0 | AT95: =AU95+AV95 -> 0 | AU95: =AW95*$BA95/100 -> 0 | AV95: =AW95*$BB95/100 -> 0 | AX95: =B95+F95+J95+N95+R95+V95+Z95+AD95+AH95+AL95+AP95+AT95 -> 0 | AY95: =C95+G95+K95+O95+S95+W95+AA95+AE95+AI95+AM95+AQ95+AU95 -> 0 | AZ95: =D95+H95+L95+P95+T95+X95+AB95+AF95+AJ95+AN95+AR95+AV95 -> 0 | BA95: =BC$1 -> 100 | BB95: =100-BA95 -> 0 | BC95: =AX95*(BB95/100) -> 0
A96: Crachás | B96: =C96+D96 -> 0 | F96: =G96+H96 -> 0 | J96: =K96+L96 -> 0 | N96: =O96+P96 -> 0 | R96: =S96+T96 -> 0 | V96: =W96+X96 -> 0 | Z96: =AA96+AB96 -> 0 | AD96: =AE96+AF96 -> 0 | AH96: =AI96+AJ96 -> 0 | AL96: =AM96+AN96 -> 0 | AP96: =AQ96+AR96 -> 0 | AT96: =AU96+AV96 -> 0 | AX96: =B96+F96+J96+N96+R96+V96+Z96+AD96+AH96+AL96+AP96+AT96 -> 0 | AY96: =C96+G96+K96+O96+S96+W96+AA96+AE96+AI96+AM96+AQ96+AU96 -> 0 | AZ96: =D96+H96+L96+P96+T96+X96+AB96+AF96+AJ96+AN96+AR96+AV96 -> 0
A97: Documentação | B97: =C97+D97 -> 700 | C97: =E97*$BA97/100 -> 700 | D97: =E97*$BB97/100 -> 0 | E97: 700 | F97: =G97+H97 -> 0 | J97: =K97+L97 -> 0 | N97: =O97+P97 -> 0 | R97: =S97+T97 -> 0 | V97: =W97+X97 -> 0 | Z97: =AA97+AB97 -> 0 | AD97: =AE97+AF97 -> 0 | AH97: =AI97+AJ97 -> 0 | AL97: =AM97+AN97 -> 0 | AP97: =AQ97+AR97 -> 0 | AT97: =AU97+AV97 -> 0 | AX97: =B97+F97+J97+N97+R97+V97+Z97+AD97+AH97+AL97+AP97+AT97 -> 700 | AY97: =C97+G97+K97+O97+S97+W97+AA97+AE97+AI97+AM97+AQ97+AU97 -> 700 | AZ97: =D97+H97+L97+P97+T97+X97+AB97+AF97+AJ97+AN97+AR97+AV97 -> 0 | BA97: =BC$1 -> 100 | BB97: =100-BA97 -> 0 | BC97: =AX97*(BB97/100) -> 0
A98: Taxa de franquia | B98: =C98+D98 -> 0 | F98: =G98+H98 -> 0 | J98: =K98+L98 -> 0 | N98: =O98+P98 -> 0 | R98: =S98+T98 -> 0 | V98: =W98+X98 -> 0 | Z98: =AA98+AB98 -> 0 | AD98: =AE98+AF98 -> 0 | AH98: =AI98+AJ98 -> 0 | AL98: =AM98+AN98 -> 0 | AP98: =AQ98+AR98 -> 0 | AT98: =AU98+AV98 -> 0 | AX98: =B98+F98+J98+N98+R98+V98+Z98+AD98+AH98+AL98+AP98+AT98 -> 0 | AY98: =C98+G98+K98+O98+S98+W98+AA98+AE98+AI98+AM98+AQ98+AU98 -> 0 | AZ98: =D98+H98+L98+P98+T98+X98+AB98+AF98+AJ98+AN98+AR98+AV98 -> 0
A99: Treinamento | B99: =C99+D99 -> 0 | C99: =E99*$BA99/100 -> 0 | D99: =E99*$BB99/100 -> 0 | F99: =G99+H99 -> 0 | G99: =I99*$BA99/100 -> 0 | H99: =I99*$BB99/100 -> 0 | J99: =K99+L99 -> 0 | K99: =M99*$BA99/100 -> 0 | L99: =M99*$BB99/100 -> 0 | N99: =O99+P99 -> 0 | O99: =Q99*$BA99/100 -> 0 | P99: =Q99*$BB99/100 -> 0 | R99: =S99+T99 -> 0 | S99: =U99*$BA99/100 -> 0 | T99: =U99*$BB99/100 -> 0 | V99: =W99+X99 -> 0 | W99: =Y99*$BA99/100 -> 0 | X99: =Y99*$BB99/100 -> 0 | Z99: =AA99+AB99 -> 0 | AA99: =AC99*$BA99/100 -> 0 | AB99: =AC99*$BB99/100 -> 0 | AD99: =AE99+AF99 -> 0 | AE99: =AG99*$BA99/100 -> 0 | AF99: =AG99*$BB99/100 -> 0 | AH99: =AI99+AJ99 -> 0 | AI99: =AK99*$BA99/100 -> 0 | AJ99: =AK99*$BB99/100 -> 0 | AL99: =AM99+AN99 -> 0 | AM99: =AO99*$BA99/100 -> 0 | AN99: =AO99*$BB99/100 -> 0 | AP99: =AQ99+AR99 -> 0 | AQ99: =AS99*$BA99/100 -> 0 | AR99: =AS99*$BB99/100 -> 0 | AT99: =AU99+AV99 -> 0 | AU99: =AW99*$BA99/100 -> 0 | AV99: =AW99*$BB99/100 -> 0 | AX99: =B99+F99+J99+N99+R99+V99+Z99+AD99+AH99+AL99+AP99+AT99 -> 0 | AY99: =C99+G99+K99+O99+S99+W99+AA99+AE99+AI99+AM99+AQ99+AU99 -> 0 | AZ99: =D99+H99+L99+P99+T99+X99+AB99+AF99+AJ99+AN99+AR99+AV99 -> 0 | BA99: 80 | BB99: =100-BA99 -> 20 | BC99: =AX99*(BB99/100) -> 0
A100: Sul America | B100: =C100+D100 -> 0 | F100: =G100+H100 -> 0 | J100: =K100+L100 -> 0 | N100: =O100+P100 -> 0 | R100: =S100+T100 -> 0 | V100: =W100+X100 -> 0 | Z100: =AA100+AB100 -> 0 | AD100: =AE100+AF100 -> 0 | AH100: =AI100+AJ100 -> 0 | AL100: =AM100+AN100 -> 0 | AP100: =AQ100+AR100 -> 0 | AT100: =AU100+AV100 -> 0 | AX100: =B100+F100+J100+N100+R100+V100+Z100+AD100+AH100+AL100+AP100+AT100 -> 0 | AY100: =C100+G100+K100+O100+S100+W100+AA100+AE100+AI100+AM100+AQ100+AU100 -> 0 | AZ100: =D100+H100+L100+P100+T100+X100+AB100+AF100+AJ100+AN100+AR100+AV100 -> 0
...

Sheet FOLHA DE PAGAMENTOS
B1: 46023 | F1: 46054 | J1: 46082 | N1: 46113 | R1: 46143 | V1: 46174 | Z1: 46204 | AD1: 46235 | AH1: 46266 | AL1: 46296 | AP1: 46327 | AT1: 46357 | AY1: VENDA | AZ1: LOCAÇÃO
B2: TOTAL | C2: VENDA | D2: ALUGUEL | F2: TOTAL | G2: VENDA | H2: ALUGUEL | J2: TOTAL | K2: VENDA | L2: ALUGUEL | N2: TOTAL | O2: VENDA | P2: ALUGUEL | R2: TOTAL | S2: VENDA | T2: ALUGUEL | V2: TOTAL | W2: VENDA | X2: ALUGUEL | Z2: TOTAL | AA2: VENDA | AB2: ALUGUEL | AD2: TOTAL | AE2: VENDA | AF2: ALUGUEL | AH2: TOTAL | AI2: VENDA | AJ2: ALUGUEL | AL2: TOTAL | AM2: VENDA | AN2: ALUGUEL | AP2: TOTAL | AQ2: VENDA | AR2: ALUGUEL | AT2: TOTAL | AU2: VENDA | AV2: ALUGUEL | AX2: TOTAL | AY2: VENDA | AZ2: ALUGUEL
A3: FOLHA DE PAGAMENTO VENDA
A4: CIEE/Agiel | B4: =C4+D4 -> 0 | F4: =G4+H4 -> 0 | J4: =K4+L4 -> 0 | N4: =O4+P4 -> 0 | R4: =S4+T4 -> 0 | V4: =W4+X4 -> 0 | Z4: =AA4+AB4 -> 0 | AD4: =AE4+AF4 -> 0 | AH4: =AI4+AJ4 -> 0 | AL4: =AM4+AN4 -> 0 | AP4: =AQ4+AR4 -> 0 | AT4: =AU4+AV4 -> 0 | AX4: =AY4+AZ4 -> 0 | AY4: =C4+G4+K4+O4+S4+W4+AA4+AE4+AI4+AM4+AQ4+AU4 -> 0 | AZ4: =D4+H4+L4+P4+T4+X4+AB4+AF4+AJ4+AN4+AR4+AV4 -> 0
A5: Estagio-seguro | B5: =C5+D5 -> 0 | F5: =G5+H5 -> 0 | J5: =K5+L5 -> 0 | N5: =O5+P5 -> 0 | R5: =S5+T5 -> 0 | V5: =W5+X5 -> 0 | Z5: =AA5+AB5 -> 0 | AD5: =AE5+AF5 -> 0 | AH5: =AI5+AJ5 -> 0 | AL5: =AM5+AN5 -> 0 | AP5: =AQ5+AR5 -> 0 | AT5: =AU5+AV5 -> 0 | AX5: =AY5+AZ5 -> 0 | AY5: =C5+G5+K5+O5+S5+W5+AA5+AE5+AI5+AM5+AQ5+AU5 -> 0 | AZ5: =D5+H5+L5+P5+T5+X5+AB5+AF5+AJ5+AN5+AR5+AV5 -> 0
A6: Pro-labore | B6: =C6+D6 -> 0 | F6: =G6+H6 -> 0 | J6: =K6+L6 -> 0 | N6: =O6+P6 -> 0 | R6: =S6+T6 -> 0 | V6: =W6+X6 -> 0 | Z6: =AA6+AB6 -> 0 | AD6: =AE6+AF6 -> 0 | AH6: =AI6+AJ6 -> 0 | AL6: =AM6+AN6 -> 0 | AP6: =AQ6+AR6 -> 0 | AT6: =AU6+AV6 -> 0 | AX6: =AY6+AZ6 -> 0 | AY6: =C6+G6+K6+O6+S6+W6+AA6+AE6+AI6+AM6+AQ6+AU6 -> 0 | AZ6: =D6+H6+L6+P6+T6+X6+AB6+AF6+AJ6+AN6+AR6+AV6 -> 0
A7: Contratos - Rafael | B7: =C7+D7 -> 0 | F7: =G7+H7 -> 0 | J7: =K7+L7 -> 0 | N7: =O7+P7 -> 0 | R7: =S7+T7 -> 0 | V7: =W7+X7 -> 0 | Z7: =AA7+AB7 -> 0 | AD7: =AE7+AF7 -> 0 | AH7: =AI7+AJ7 -> 0 | AL7: =AM7+AN7 -> 0 | AP7: =AQ7+AR7 -> 0 | AT7: =AU7+AV7 -> 0 | AX7: =AY7+AZ7 -> 0 | AY7: =C7+G7+K7+O7+S7+W7+AA7+AE7+AI7+AM7+AQ7+AU7 -> 0 | AZ7: =D7+H7+L7+P7+T7+X7+AB7+AF7+AJ7+AN7+AR7+AV7 -> 0
A8: VA | B8: =C8+D8 -> 0 | F8: =G8+H8 -> 0 | J8: =K8+L8 -> 0 | N8: =O8+P8 -> 0 | R8: =S8+T8 -> 0 | V8: =W8+X8 -> 0 | Z8: =AA8+AB8 -> 0 | AD8: =AE8+AF8 -> 0 | AH8: =AI8+AJ8 -> 0 | AL8: =AM8+AN8 -> 0 | AP8: =AQ8+AR8 -> 0 | AT8: =AU8+AV8 -> 0 | AX8: =AY8+AZ8 -> 0 | AY8: =C8+G8+K8+O8+S8+W8+AA8+AE8+AI8+AM8+AQ8+AU8 -> 0 | AZ8: =D8+H8+L8+P8+T8+X8+AB8+AF8+AJ8+AN8+AR8+AV8 -> 0
A9: VT | B9: =C9+D9 -> 0 | F9: =G9+H9 -> 0 | J9: =K9+L9 -> 0 | N9: =O9+P9 -> 0 | R9: =S9+T9 -> 0 | V9: =W9+X9 -> 0 | Z9: =AA9+AB9 -> 0 | AD9: =AE9+AF9 -> 0 | AH9: =AI9+AJ9 -> 0 | AL9: =AM9+AN9 -> 0 | AP9: =AQ9+AR9 -> 0 | AT9: =AU9+AV9 -> 0 | AX9: =AY9+AZ9 -> 0 | AY9: =C9+G9+K9+O9+S9+W9+AA9+AE9+AI9+AM9+AQ9+AU9 -> 0 | AZ9: =D9+H9+L9+P9+T9+X9+AB9+AF9+AJ9+AN9+AR9+AV9 -> 0
A10: Recepção | B10: =C10+D10 -> 0 | F10: =G10+H10 -> 0 | J10: =K10+L10 -> 0 | N10: =O10+P10 -> 0 | R10: =S10+T10 -> 0 | V10: =W10+X10 -> 0 | Z10: =AA10+AB10 -> 0 | AD10: =AE10+AF10 -> 0 | AH10: =AI10+AJ10 -> 0 | AL10: =AM10+AN10 -> 0 | AP10: =AQ10+AR10 -> 0 | AT10: =AU10+AV10 -> 0 | AX10: =AY10+AZ10 -> 0 | AY10: =C10+G10+K10+O10+S10+W10+AA10+AE10+AI10+AM10+AQ10+AU10 -> 0 | AZ10: =D10+H10+L10+P10+T10+X10+AB10+AF10+AJ10+AN10+AR10+AV10 -> 0
A11: VA | B11: =C11+D11 -> 0 | F11: =G11+H11 -> 0 | J11: =K11+L11 -> 0 | N11: =O11+P11 -> 0 | R11: =S11+T11 -> 0 | V11: =W11+X11 -> 0 | Z11: =AA11+AB11 -> 0 | AD11: =AE11+AF11 -> 0 | AH11: =AI11+AJ11 -> 0 | AL11: =AM11+AN11 -> 0 | AP11: =AQ11+AR11 -> 0 | AT11: =AU11+AV11 -> 0 | AX11: =AY11+AZ11 -> 0 | AY11: =C11+G11+K11+O11+S11+W11+AA11+AE11+AI11+AM11+AQ11+AU11 -> 0 | AZ11: =D11+H11+L11+P11+T11+X11+AB11+AF11+AJ11+AN11+AR11+AV11 -> 0
A12: VT | B12: =C12+D12 -> 0 | F12: =G12+H12 -> 0 | J12: =K12+L12 -> 0 | N12: =O12+P12 -> 0 | R12: =S12+T12 -> 0 | V12: =W12+X12 -> 0 | Z12: =AA12+AB12 -> 0 | AD12: =AE12+AF12 -> 0 | AH12: =AI12+AJ12 -> 0 | AL12: =AM12+AN12 -> 0 | AP12: =AQ12+AR12 -> 0 | AT12: =AU12+AV12 -> 0 | AX12: =AY12+AZ12 -> 0 | AY12: =C12+G12+K12+O12+S12+W12+AA12+AE12+AI12+AM12+AQ12+AU12 -> 0 | AZ12: =D12+H12+L12+P12+T12+X12+AB12+AF12+AJ12+AN12+AR12+AV12 -> 0
A13: substituição das Férias | B13: =C13+D13 -> 0 | F13: =G13+H13 -> 0 | J13: =K13+L13 -> 0 | N13: =O13+P13 -> 0 | R13: =S13+T13 -> 0 | V13: =W13+X13 -> 0 | Z13: =AA13+AB13 -> 0 | AD13: =AE13+AF13 -> 0 | AH13: =AI13+AJ13 -> 0 | AL13: =AM13+AN13 -> 0 | AP13: =AQ13+AR13 -> 0 | AT13: =AU13+AV13 -> 0 | AX13: =AY13+AZ13 -> 0 | AY13: =C13+G13+K13+O13+S13+W13+AA13+AE13+AI13+AM13+AQ13+AU13 -> 0 | AZ13: =D13+H13+L13+P13+T13+X13+AB13+AF13+AJ13+AN13+AR13+AV13 -> 0
A14: Recepção- Giovana | B14: =C14+D14 -> 0 | F14: =G14+H14 -> 0 | J14: =K14+L14 -> 0 | N14: =O14+P14 -> 0 | R14: =S14+T14 -> 0 | V14: =W14+X14 -> 0 | Z14: =AA14+AB14 -> 0 | AD14: =AE14+AF14 -> 0 | AH14: =AI14+AJ14 -> 0 | AL14: =AM14+AN14 -> 0 | AP14: =AQ14+AR14 -> 0 | AT14: =AU14+AV14 -> 0 | AX14: =AY14+AZ14 -> 0 | AY14: =C14+G14+K14+O14+S14+W14+AA14+AE14+AI14+AM14+AQ14+AU14 -> 0 | AZ14: =D14+H14+L14+P14+T14+X14+AB14+AF14+AJ14+AN14+AR14+AV14 -> 0
A15: VA | B15: =C15+D15 -> 0 | F15: =G15+H15 -> 0 | J15: =K15+L15 -> 0 | N15: =O15+P15 -> 0 | R15: =S15+T15 -> 0 | V15: =W15+X15 -> 0 | Z15: =AA15+AB15 -> 0 | AD15: =AE15+AF15 -> 0 | AH15: =AI15+AJ15 -> 0 | AL15: =AM15+AN15 -> 0 | AP15: =AQ15+AR15 -> 0 | AT15: =AU15+AV15 -> 0 | AX15: =AY15+AZ15 -> 0 | AY15: =C15+G15+K15+O15+S15+W15+AA15+AE15+AI15+AM15+AQ15+AU15 -> 0 | AZ15: =D15+H15+L15+P15+T15+X15+AB15+AF15+AJ15+AN15+AR15+AV15 -> 0
... A19: VT | B19: =C19+D19 -> 0 | F19: =G19+H19 -> 0 | J19: =K19+L19 -> 0 | N19: =O19+P19 -> 0 | R19: =S19+T19 -> 0 | V19: =W19+X19 -> 0 | Z19: =AA19+AB19 -> 0 | AD19: =AE19+AF19 -> 0 | AH19: =AI19+AJ19 -> 0 | AL19: =AM19+AN19 -> 0 | AP19: =AQ19+AR19 -> 0 | AT19: =AU19+AV19 -> 0 | AX19: =AY19+AZ19 -> 0 | AY19: =C19+G19+K19+O19+S19+W19+AA19+AE19+AI19+AM19+AQ19+AU19 -> 0 | AZ19: =D19+H19+L19+P19+T19+X19+AB19+AF19+AJ19+AN19+AR19+AV19 -> 0
A20: TOTAL | B20: =SUM(B4:B19) -> 0 | C20: =SUM(C4:C19) -> 0 | D20: =SUM(D4:D19) -> 0 | F20: =SUM(F4:F19) -> 0 | G20: =SUM(G4:G19) -> 0 | H20: =SUM(H4:H19) -> 0 | J20: =SUM(J4:J19) -> 0 | K20: =SUM(K4:K19) -> 0 | L20: =SUM(L4:L19) -> 0 | N20: =SUM(N4:N19) -> 0 | O20: =SUM(O4:O19) -> 0 | P20: =SUM(P4:P19) -> 0 | R20: =SUM(R4:R19) -> 0 | S20: =SUM(S4:S19) -> 0 | T20: =SUM(T4:T19) -> 0 | V20: =SUM(V4:V19) -> 0 | W20: =SUM(W4:W19) -> 0 | X20: =SUM(X4:X19) -> 0 | Z20: =SUM(Z4:Z19) -> 0 | AA20: =SUM(AA4:AA19) -> 0 | AB20: =SUM(AB4:AB19) -> 0 | AD20: =SUM(AD4:AD19) -> 0 | AE20: =SUM(AE4:AE19) -> 0 | AF20: =SUM(AF4:AF19) -> 0 | AH20: =SUM(AH4:AH19) -> 0 | AI20: =SUM(AI4:AI19) -> 0 | AJ20: =SUM(AJ4:AJ19) -> 0 | AL20: =SUM(AL4:AL19) -> 0 | AM20: =SUM(AM4:AM19) -> 0 | AN20: =SUM(AN4:AN19) -> 0 | AP20: =SUM(AP4:AP19) -> 0 | AQ20: =SUM(AQ4:AQ19) -> 0 | AR20: =SUM(AR4:AR19) -> 0 | AT20: =SUM(AT4:AT19) -> 0 | AU20: =SUM(AU4:AU19) -> 0 | AV20: =SUM(AV4:AV19) -> 0 | AX20: =SUM(AX4:AX19) -> 0 | AY20: =SUM(AY4:AY19) -> 0 | AZ20: =SUM(AZ4:AZ19) -> 0
A21: FOLHA DE PAGAMENTO ALUGUEL
A22: Ana Paula - Consultora | B22: =C22+D22 -> 0 | F22: =G22+H22 -> 0 | J22: =K22+L22 -> 0 | N22: =O22+P22 -> 0 | R22: =S22+T22 -> 0 | V22: =W22+X22 -> 0 | Z22: =AA22+AB22 -> 0 | AD22: =AE22+AF22 -> 0 | AH22: =AI22+AJ22 -> 0 | AL22: =AM22+AN22 -> 0 | AP22: =AQ22+AR22 -> 0 | AT22: =AU22+AV22 -> 0 | AX22: =AY22+AZ22 -> 0 | AY22: =C22+G22+K22+O22+S22+W22+AA22+AE22+AI22+AM22+AQ22+AU22 -> 0 | AZ22: =D22+H22+L22+P22+T22+X22+AB22+AF22+AJ22+AN22+AR22+AV22 -> 0
A23: VA | B23: =C23+D23 -> 0 | F23: =G23+H23 -> 0 | J23: =K23+L23 -> 0 | N23: =O23+P23 -> 0 | R23: =S23+T23 -> 0 | V23: =W23+X23 -> 0 | Z23: =AA23+AB23 -> 0 | AD23: =AE23+AF23 -> 0 | AH23: =AI23+AJ23 -> 0 | AL23: =AM23+AN23 -> 0 | AP23: =AQ23+AR23 -> 0 | AT23: =AU23+AV23 -> 0 | AX23: =AY23+AZ23 -> 0 | AY23: =C23+G23+K23+O23+S23+W23+AA23+AE23+AI23+AM23+AQ23+AU23 -> 0 | AZ23: =D23+H23+L23+P23+T23+X23+AB23+AF23+AJ23+AN23+AR23+AV23 -> 0
A24: VT | B24: =C24+D24 -> 0 | F24: =G24+H24 -> 0 | J24: =K24+L24 -> 0 | N24: =O24+P24 -> 0 | R24: =S24+T24 -> 0 | V24: =W24+X24 -> 0 | Z24: =AA24+AB24 -> 0 | AD24: =AE24+AF24 -> 0 | AH24: =AI24+AJ24 -> 0 | AL24: =AM24+AN24 -> 0 | AP24: =AQ24+AR24 -> 0 | AT24: =AU24+AV24 -> 0 | AX24: =AY24+AZ24 -> 0 | AY24: =C24+G24+K24+O24+S24+W24+AA24+AE24+AI24+AM24+AQ24+AU24 -> 0 | AZ24: =D24+H24+L24+P24+T24+X24+AB24+AF24+AJ24+AN24+AR24+AV24 -> 0
A25: Roberta - Consultora | B25: =C25+D25 -> 0 | F25: =G25+H25 -> 0 | J25: =K25+L25 -> 0 | N25: =O25+P25 -> 0 | R25: =S25+T25 -> 0 | V25: =W25+X25 -> 0 | Z25: =AA25+AB25 -> 0 | AD25: =AE25+AF25 -> 0 | AH25: =AI25+AJ25 -> 0 | AL25: =AM25+AN25 -> 0 | AP25: =AQ25+AR25 -> 0 | AT25: =AU25+AV25 -> 0 | AX25: =AY25+AZ25 -> 0 | AY25: =C25+G25+K25+O25+S25+W25+AA25+AE25+AI25+AM25+AQ25+AU25 -> 0 | AZ25: =D25+H25+L25+P25+T25+X25+AB25+AF25+AJ25+AN25+AR25+AV25 -> 0
A26: VA | B26: =C26+D26 -> 0 | F26: =G26+H26 -> 0 | J26: =K26+L26 -> 0 | N26: =O26+P26 -> 0 | R26: =S26+T26 -> 0 | V26: =W26+X26 -> 0 | Z26: =AA26+AB26 -> 0 | AD26: =AE26+AF26 -> 0 | AH26: =AI26+AJ26 -> 0 | AL26: =AM26+AN26 -> 0 | AP26: =AQ26+AR26 -> 0 | AT26: =AU26+AV26 -> 0 | AX26: =AY26+AZ26 -> 0 | AY26: =C26+G26+K26+O26+S26+W26+AA26+AE26+AI26+AM26+AQ26+AU26 -> 0 | AZ26: =D26+H26+L26+P26+T26+X26+AB26+AF26+AJ26+AN26+AR26+AV26 -> 0
A27: VT | B27: =C27+D27 -> 0 | F27: =G27+H27 -> 0 | J27: =K27+L27 -> 0 | N27: =O27+P27 -> 0 | R27: =S27+T27 -> 0 | V27: =W27+X27 -> 0 | Z27: =AA27+AB27 -> 0 | AD27: =AE27+AF27 -> 0 | AH27: =AI27+AJ27 -> 0 | AL27: =AM27+AN27 -> 0 | AP27: =AQ27+AR27 -> 0 | AT27: =AU27+AV27 -> 0 | AX27: =AY27+AZ27 -> 0 | AY27: =C27+G27+K27+O27+S27+W27+AA27+AE27+AI27+AM27+AQ27+AU27 -> 0 | AZ27: =D27+H27+L27+P27+T27+X27+AB27+AF27+AJ27+AN27+AR27+AV27 -> 0
A28: Michele - Captadora | B28: =C28+D28 -> 0 | F28: =G28+H28 -> 0 | J28: =K28+L28 -> 0 | N28: =O28+P28 -> 0 | R28: =S28+T28 -> 0 | V28: =W28+X28 -> 0 | Z28: =AA28+AB28 -> 0 | AD28: =AE28+AF28 -> 0 | AH28: =AI28+AJ28 -> 0 | AL28: =AM28+AN28 -> 0 | AP28: =AQ28+AR28 -> 0 | AT28: =AU28+AV28 -> 0 | AX28: =AY28+AZ28 -> 0 | AY28: =C28+G28+K28+O28+S28+W28+AA28+AE28+AI28+AM28+AQ28+AU28 -> 0 | AZ28: =D28+H28+L28+P28+T28+X28+AB28+AF28+AJ28+AN28+AR28+AV28 -> 0
A29: VA | B29: =C29+D29 -> 0 | F29: =G29+H29 -> 0 | J29: =K29+L29 -> 0 | N29: =O29+P29 -> 0 | R29: =S29+T29 -> 0 | V29: =W29+X29 -> 0 | Z29: =AA29+AB29 -> 0 | AD29: =AE29+AF29 -> 0 | AH29: =AI29+AJ29 -> 0 | AL29: =AM29+AN29 -> 0 | AP29: =AQ29+AR29 -> 0 | AT29: =AU29+AV29 -> 0 | AX29: =AY29+AZ29 -> 0 | AY29: =C29+G29+K29+O29+S29+W29+AA29+AE29+AI29+AM29+AQ29+AU29 -> 0 | AZ29: =D29+H29+L29+P29+T29+X29+AB29+AF29+AJ29+AN29+AR29+AV29 -> 0
A30: VT | B30: =C30+D30 -> 0 | F30: =G30+H30 -> 0 | J30: =K30+L30 -> 0 | N30: =O30+P30 -> 0 | R30: =S30+T30 -> 0 | V30: =W30+X30 -> 0 | Z30: =AA30+AB30 -> 0 | AD30: =AE30+AF30 -> 0 | AH30: =AI30+AJ30 -> 0 | AL30: =AM30+AN30 -> 0 | AP30: =AQ30+AR30 -> 0 | AT30: =AU30+AV30 -> 0 | AX30: =AY30+AZ30 -> 0 | AY30: =C30+G30+K30+O30+S30+W30+AA30+AE30+AI30+AM30+AQ30+AU30 -> 0 | AZ30: =D30+H30+L30+P30+T30+X30+AB30+AF30+AJ30+AN30+AR30+AV30 -> 0
A31: Vitória - Captadora | B31: =C31+D31 -> 0 | F31: =G31+H31 -> 0 | J31: =K31+L31 -> 0 | N31: =O31+P31 -> 0 | R31: =S31+T31 -> 0 | V31: =W31+X31 -> 0 | Z31: =AA31+AB31 -> 0 | AD31: =AE31+AF31 -> 0 | AH31: =AI31+AJ31 -> 0 | AL31: =AM31+AN31 -> 0 | AP31: =AQ31+AR31 -> 0 | AT31: =AU31+AV31 -> 0 | AX31: =AY31+AZ31 -> 0 | AY31: =C31+G31+K31+O31+S31+W31+AA31+AE31+AI31+AM31+AQ31+AU31 -> 0 | AZ31: =D31+H31+L31+P31+T31+X31+AB31+AF31+AJ31+AN31+AR31+AV31 -> 0
A32: VA | B32: =C32+D32 -> 0 | F32: =G32+H32 -> 0 | J32: =K32+L32 -> 0 | N32: =O32+P32 -> 0 | R32: =S32+T32 -> 0 | V32: =W32+X32 -> 0 | Z32: =AA32+AB32 -> 0 | AD32: =AE32+AF32 -> 0 | AH32: =AI32+AJ32 -> 0 | AL32: =AM32+AN32 -> 0 | AP32: =AQ32+AR32 -> 0 | AT32: =AU32+AV32 -> 0 | AX32: =AY32+AZ32 -> 0 | AY32: =C32+G32+K32+O32+S32+W32+AA32+AE32+AI32+AM32+AQ32+AU32 -> 0 | AZ32: =D32+H32+L32+P32+T32+X32+AB32+AF32+AJ32+AN32+AR32+AV32 -> 0
A33: VT | B33: =C33+D33 -> 0 | F33: =G33+H33 -> 0 | J33: =K33+L33 -> 0 | N33: =O33+P33 -> 0 | R33: =S33+T33 -> 0 | V33: =W33+X33 -> 0 | Z33: =AA33+AB33 -> 0 | AD33: =AE33+AF33 -> 0 | AH33: =AI33+AJ33 -> 0 | AL33: =AM33+AN33 -> 0 | AP33: =AQ33+AR33 -> 0 | AT33: =AU33+AV33 -> 0 | AX33: =AY33+AZ33 -> 0 | AY33: =C33+G33+K33+O33+S33+W33+AA33+AE33+AI33+AM33+AQ33+AU33 -> 0 | AZ33: =D33+H33+L33+P33+T33+X33+AB33+AF33+AJ33+AN33+AR33+AV33 -> 0
... A53: PROJETO HUB | B53: =C53+D53 -> 0 | F53: =G53+H53 -> 0 | J53: =K53+L53 -> 0 | N53: =O53+P53 -> 0 | R53: =S53+T53 -> 0 | V53: =W53+X53 -> 0 | Z53: =AA53+AB53 -> 0 | AD53: =AE53+AF53 -> 0 | AH53: =AI53+AJ53 -> 0 | AL53: =AM53+AN53 -> 0 | AP53: =AQ53+AR53 -> 0 | AT53: =AU53+AV53 -> 0 | AX53: =AY53+AZ53 -> 0 | AY53: =C53+G53+K53+O53+S53+W53+AA53+AE53+AI53+AM53+AQ53+AU53 -> 0 | AZ53: =D53+H53+L53+P53+T53+X53+AB53+AF53+AJ53+AN53+AR53+AV53 -> 0
B54: =C54+D54 -> 0 | F54: =G54+H54 -> 0 | J54: =K54+L54 -> 0 | N54: =O54+P54 -> 0 | R54: =S54+T54 -> 0 | V54: =W54+X54 -> 0 | Z54: =AA54+AB54 -> 0 | AD54: =AE54+AF54 -> 0 | AH54: =AI54+AJ54 -> 0 | AL54: =AM54+AN54 -> 0 | AP54: =AQ54+AR54 -> 0 | AT54: =AU54+AV54 -> 0 | AX54: =AY54+AZ54 -> 0 | AY54: =C54+G54+K54+O54+S54+W54+AA54+AE54+AI54+AM54+AQ54+AU54 -> 0 | AZ54: =D54+H54+L54+P54+T54+X54+AB54+AF54+AJ54+AN54+AR54+AV54 -> 0
A55: TOTAL | B55: =SUM(B22:B54) -> 0 | C55: =SUM(C22:C54) -> 0 | D55: =SUM(D22:D54) -> 0 | F55: =SUM(F22:F54) -> 0 | G55: =SUM(G22:G54) -> 0 | H55: =SUM(H22:H54) -> 0 | J55: =SUM(J22:J54) -> 0 | K55: =SUM(K22:K54) -> 0 | L55: =SUM(L22:L54) -> 0 | N55: =SUM(N22:N54) -> 0 | O55: =SUM(O22:O54) -> 0 | P55: =SUM(P22:P54) -> 0 | R55: =SUM(R22:R54) -> 0 | S55: =SUM(S22:S54) -> 0 | T55: =SUM(T22:T54) -> 0 | V55: =SUM(V22:V54) -> 0 | W55: =SUM(W22:W54) -> 0 | X55: =SUM(X22:X54) -> 0 | Z55: =SUM(Z22:Z54) -> 0 | AA55: =SUM(AA22:AA54) -> 0 | AB55: =SUM(AB22:AB54) -> 0 | AD55: =SUM(AD22:AD54) -> 0 | AE55: =SUM(AE22:AE54) -> 0 | AF55: =SUM(AF22:AF54) -> 0 | AH55: =SUM(AH22:AH54) -> 0 | AI55: =SUM(AI22:AI54) -> 0 | AJ55: =SUM(AJ22:AJ54) -> 0 | AL55: =SUM(AL22:AL54) -> 0 | AM55: =SUM(AM22:AM54) -> 0 | AN55: =SUM(AN22:AN54) -> 0 | AP55: =SUM(AP22:AP54) -> 0 | AQ55: =SUM(AQ22:AQ54) -> 0 | AR55: =SUM(AR22:AR54) -> 0 | AT55: =SUM(AT22:AT54) -> 0 | AU55: =SUM(AU22:AU54) -> 0 | AV55: =SUM(AV22:AV54) -> 0 | AX55: =SUM(AX22:AX54) -> 0 | AY55: =SUM(AY22:AY54) -> 0 | AZ55: =SUM(AZ22:AZ54) -> 0
A57: RESUMO DA FOLHA | B57: =B20+B55 -> 0 | C57: =C20+C55 -> 0 | D57: =D20+D55 -> 0 | F57: =F20+F55 -> 0 | G57: =G20+G55 -> 0 | H57: =H20+H55 -> 0 | J57: =J20+J55 -> 0 | K57: =K20+K55 -> 0 | L57: =L20+L55 -> 0 | N57: =N20+N55 -> 0 | O57: =O20+O55 -> 0 | P57: =P20+P55 -> 0 | R57: =R20+R55 -> 0 | S57: =S20+S55 -> 0 | T57: =T20+T55 -> 0 | V57: =V20+V55 -> 0 | W57: =W20+W55 -> 0 | X57: =X20+X55 -> 0 | Z57: =Z20+Z55 -> 0 | AA57: =AA20+AA55 -> 0 | AB57: =AB20+AB55 -> 0 | AD57: =AD20+AD55 -> 0 | AE57: =AE20+AE55 -> 0 | AF57: =AF20+AF55 -> 0 | AH57: =AH20+AH55 -> 0 | AI57: =AI20+AI55 -> 0 | AJ57: =AJ20+AJ55 -> 0 | AL57: =AL20+AL55 -> 0 | AM57: =AM20+AM55 -> 0 | AN57: =AN20+AN55 -> 0 | AP57: =AP20+AP55 -> 0 | AQ57: =AQ20+AQ55 -> 0 | AR57: =AR20+AR55 -> 0 | AT57: =AT20+AT55 -> 0 | AU57: =AU20+AU55 -> 0 | AV57: =AV20+AV55 -> 0 | AX57: =AX20+AX55 -> 0 | AY57: =AY20+AY55 -> 0 | AZ57: =AZ20+AZ55 -> 0
A58: Participação | C58: =IF(B57=0,0,C57/B57) -> 0 | D58: =IF(B57=0,0,D57/B57) -> 0 | G58: =IF(F57=0,0,G57/F57) -> 0 | H58: =IF(F57=0,0,H57/F57) -> 0 | K58: =IF(J57=0,0,K57/J57) -> 0 | L58: =IF(J57=0,0,L57/J57) -> 0 | O58: =IF(N57=0,0,O57/N57) -> 0 | P58: =IF(N57=0,0,P57/N57) -> 0 | S58: =IF(R57=0,0,S57/R57) -> 0 | T58: =IF(R57=0,0,T57/R57) -> 0 | W58: =IF(V57=0,0,W57/V57) -> 0 | X58: =IF(V57=0,0,X57/V57) -> 0 | AA58: =IF(Z57=0,0,AA57/Z57) -> 0 | AB58: =IF(Z57=0,0,AB57/Z57) -> 0 | AE58: =IF(AD57=0,0,AE57/AD57) -> 0 | AF58: =IF(AD57=0,0,AF57/AD57) -> 0 | AI58: =IF(AH57=0,0,AI57/AH57) -> 0 | AJ58: =IF(AH57=0,0,AJ57/AH57) -> 0 | AM58: =IF(AL57=0,0,AM57/AL57) -> 0 | AN58: =IF(AL57=0,0,AN57/AL57) -> 0 | AQ58: =IF(AP57=0,0,AQ57/AP57) -> 0 | AR58: =IF(AP57=0,0,AR57/AP57) -> 0 | AU58: =IF(AT57=0,0,AU57/AT57) -> 0 | AV58: =IF(AT57=0,0,AV57/AT57) -> 0 | AY58: =IF(AX57=0,0,AY57/AX57) -> 0 | AZ58: =IF(AX57=0,0,AZ57/AX57) -> 0

Sheet Tarifas Bancárias
B2: DOC/TED Internet | C2: DOC/TED Pessoal | D2: Manut. Conta | E2: Manut. Crot | F2: Caixa Seguros | G2: Cartão de Crédito | H2: Seguro Residencial | I2: Deb. Cesta PJ | J2: Deb IOF | K2: Deb Juros | L2: Deb Avulso | M2: Lib talão | N2: Tar Excess | O2: Taxa Devol | P2: TR D CH | Q2: T D Din Ag | R2: Tar Saq Ag | S2: Tar SQ ATM | T2: Tar Bco24H | U2: seguradora | V2: Tar Doc In | W2: Tar Ren Car | X2: Tarifa Pix | Y2: Total
A4: 43466 | Y4: =SUM(B4:X4) -> 0
A5: 43467 | J5: 6.12 | K5: 20.9 | Y5: =SUM(B5:X5) -> 27.02
A6: 43468 | Y6: =SUM(B6:X6) -> 0
A7: 43469 | Y7: =SUM(B7:X7) -> 0
A8: 43470 | Y8: =SUM(B8:X8) -> 0
A9: 43471 | Y9: =SUM(B9:X9) -> 0
A10: 43472 | Y10: =SUM(B10:X10) -> 0
A11: 43473 | Y11: =SUM(B11:X11) -> 0
A12: 43474 | Y12: =SUM(B12:X12) -> 0
A13: 43475 | Y13: =SUM(B13:X13) -> 0
A14: 43476 | Y14: =SUM(B14:X14) -> 0
A15: 43477 | I15: 75 | Y15: =SUM(B15:X15) -> 75
A16: 43478 | Y16: =SUM(B16:X16) -> 0
A17: 43479 | Y17: =SUM(B17:X17) -> 0
A18: 43480 | X18: 0.07 | Y18: =SUM(B18:X18) -> 0.07
A19: 43481 | X19: =0.75+4 -> 4.75 | Y19: =SUM(B19:X19) -> 4.75
A20: 43482 | Y20: =SUM(B20:X20) -> 0
A21: 43483 | Y21: =SUM(B21:X21) -> 0
A22: 43484 | Y22: =SUM(B22:X22) -> 0
A23: 43485 | Y23: =SUM(B23:X23) -> 0
A24: 43486 | Y24: =SUM(B24:X24) -> 0
A25: 43487 | Y25: =SUM(B25:X25) -> 0
A26: 43488 | Y26: =SUM(B26:X26) -> 0
A27: 43489 | Y27: =SUM(B27:X27) -> 0
A28: 43490 | Y28: =SUM(B28:X28) -> 0
A29: 43491 | F29: 236.75 | X29: 1.84 | Y29: =SUM(B29:X29) -> 238.59
A30: 43492 | X30: =4+4.09 -> 8.09 | Y30: =SUM(B30:X30) -> 8.09
A31: 43493 | X31: 0.48 | Y31: =SUM(B31:X31) -> 0.48
A32: 43494 | X32: =130+8.5+6.23 -> 144.73 | Y32: =SUM(B32:X32) -> 144.73
A33: 43495 | X33: 4 | Y33: =SUM(B33:X33) -> 4
A34: 43496 | Y34: =SUM(B34:X34) -> 0
Y35: =SUM(B35:X35) -> 0
B36: =SUM(B3:B35) -> 0 | C36: =SUM(C3:C35) -> 0 | D36: =SUM(D3:D35) -> 0 | E36: =SUM(E3:E35) -> 0 | F36: =SUM(F3:F35) -> 236.75 | G36: =SUM(G3:G35) -> 0 | H36: =SUM(H3:H35) -> 0 | I36: =SUM(I3:I35) -> 75 | ... Y36: =SUM(Y3:Y35) -> 502.73
Y37: =SUM(B37:X37) -> 0
A38: 43497 | Y38: =SUM(B38:X38) -> 0
A39: 43498 | J39: 48.37 | K39: 245.87 | Y39: =SUM(B39:X39) -> 294.24
A40: 43499 | X40: 1.51 | Y40: =SUM(B40:X40) -> 1.51
A41: 43500 | X41: 4 | Y41: =SUM(B41:X41) -> 4
A42: 43501 | Y42: =SUM(B42:X42) -> 0
A43: 43502 | Y43: =SUM(B43:X43) -> 0
A44: 43503 | Y44: =SUM(B44:X44) -> 0
A45: 43504 | Y45: =SUM(B45:X45) -> 0
A46: 43505 | Y46: =SUM(B46:X46) -> 0
A47: 43506 | I47: 75 | Y47: =SUM(B47:X47) -> 75
A48: 43507 | Y48: =SUM(B48:X48) -> 0
A49: 43508 | X49: 0.44 | Y49: =SUM(B49:X49) -> 0.44
A50: 43509 | X50: 2.67 | Y50: =SUM(B50:X50) -> 2.67
A51: 43510 | Y51: =SUM(B51:X51) -> 0
A52: 43511 | Y52: =SUM(B52:X52) -> 0
A53: 43512 | Y53: =SUM(B53:X53) -> 0
A54: 43513 | Y54: =SUM(B54:X54) -> 0
A55: 43514 | Y55: =SUM(B55:X55) -> 0
A56: 43515 | Y56: =SUM(B56:X56) -> 0
A57: 43516 | X57: =8.5+8.5+1.33 -> 18.33 | Y57: =SUM(B57:X57) -> 18.33
A58: 43517 | Y58: =SUM(B58:X58) -> 0
A59: 43518 | Y59: =SUM(B59:X59) -> 0
A60: 43519 | X60: =0.13+0.96 -> 1.09 | Y60: =SUM(B60:X60) -> 1.09
A61: 43520 | X61: 8.5 | Y61: =SUM(B61:X61) -> 8.5
A62: 43521 | U62: 236.75 | X62: 0.26 | Y62: =SUM(B62:X62) -> 237.01
A63: 43522 | Y63: =SUM(B63:X63) -> 0
A64: 43523 | Y64: =SUM(B64:X64) -> 0
A65: 43524 | Y65: =SUM(B65:X65) -> 0
Y66: =SUM(B66:X66) -> 0
B67: =SUM(B37:B66) -> 0 | C67: =SUM(C37:C66) -> 0 | D67: =SUM(D37:D66) -> 0 | E67: =SUM(E37:E66) -> 0 | F67: =SUM(F37:F66) -> 0 | G67: =SUM(G37:G66) -> 0 | H67: =SUM(H37:H66) -> 0 | I67: =SUM(I37:I66) -> 75 | ... Y67: =SUM(Y37:Y66) -> 642.79
Y68: =SUM(B68:X68) -> 0
A69: 43525 | Y69: =SUM(B69:X69) -> 0
A70: 43526 | J70: 32.43 | K70: 346.66 | X70: =88.99+8.5+8.5+4.09+2.67 -> 112.75 | Y70: =SUM(B70:X70) -> 491.84
A71: 43527 | Y71: =SUM(B71:X71) -> 0
A72: 43528 | X72: =5.84+4.3 -> 10.14 | Y72: =SUM(B72:X72) -> 10.14
A73: 43529 | Y73: =SUM(B73:X73) -> 0
A74: 43530 | Y74: =SUM(B74:X74) -> 0
A75: 43531 | Y75: =SUM(B75:X75) -> 0
A76: 43532 | Y76: =SUM(B76:X76) -> 0
A77: 43533 | X77: =2.67+1.84 -> 4.51 | Y77: =SUM(B77:X77) -> 4.51
A78: 43534 | I78: 75 | X78: =2.31+8.5 -> 10.81 | Y78: =SUM(B78:X78) -> 85.81
A79: 43535 | Y79: =SUM(B79:X79) -> 0
A80: 43536 | Y80: =SUM(B80:X80) -> 0
A81: 43537 | X81: 4 | Y81: =SUM(B81:X81) -> 4
A82: 43538 | Y82: =SUM(B82:X82) -> 0
A83: 43539 | Y83: =SUM(B83:X83) -> 0
A84: 43540 | Y84: =SUM(B84:X84) -> 0
A85: 43541 | Y85: =SUM(B85:X85) -> 0
A86: 43542 | Y86: =SUM(B86:X86) -> 0
A87: 43543 | Y87: =SUM(B87:X87) -> 0
A88: 43544 | Y88: =SUM(B88:X88) -> 0
A89: 43545 | Y89: =SUM(B89:X89) -> 0
A90: 43546 | Y90: =SUM(B90:X90) -> 0
A91: 43547 | Y91: =SUM(B91:X91) -> 0
A92: 43548 | Y92: =SUM(B92:X92) -> 0
A93: 43549 | Y93: =SUM(B93:X93) -> 0
... A99: 43555 | Y99: =SUM(B99:X99) -> 0
Y100: =SUM(B100:X100) -> 0
B101: =SUM(B68:B100) -> 0 | C101: =SUM(C68:C100) -> 0 | D101: =SUM(D68:D100) -> 0 | E101: =SUM(E68:E100) -> 0 | F101: =SUM(F68:F100) -> 0 | G101: =SUM(G68:G100) -> 0 | H101: =SUM(H68:H100) -> 0 | I101: =SUM(I68:I100) -> 75 | ... Y101: =SUM(Y68:Y100) -> 596.3
Y102: =SUM(B102:X102) -> 0
A103: 43556 | Y103: =SUM(B103:X103) -> 0
A104: 43557 | Y104: =SUM(B104:X104) -> 0
A105: 43558 | Y105: =SUM(B105:X105) -> 0
A106: 43559 | Y106: =SUM(B106:X106) -> 0
A107: 43560 | Y107: =SUM(B107:X107) -> 0
...
